Workbook
Name ConflictID4: Variables!$E$9
Name PoolId6: Variables!$B$17
Name Tbl_ItemName: Items!$A$2:$C$2637
Name Tbl_EffectName: Effects!$A$2:$C$1166
Name PoolId4: Variables!$B$15
Name SelectedEffect_1: Variables!$B$6
Name ConflictID5: Variables!$E$10
Name PoolId1: Variables!$B$12
Name EffectParamUrl: Variables!$B$2
Name RelicParamUrl: Variables!$B$4
Name ConflictID3: Variables!$E$8
Name Tbl_PoolParam: EffectPoolParam!$A$2:$B$22089
Name ConflictID6: Variables!$E$11
Name SelectedEffect_3: Variables!$B$8
Name EffectPoolParamUrl: Variables!$B$3
Name PoolId5: Variables!$B$16
Name Tbl_RelicParam: RelicParam!$A$2:$H$1386
Name ConflictID2: Variables!$E$7
Name SelectedCurse_3: Variables!$B$11
Name SelectedCurse_2: Variables!$B$10
Name Tbl_ItemSource: Tables!$A$2:$C$5
Name EmptyID: Variables!$B$1
Name PoolId2: Variables!$B$13
Name ConfilctID1: Variables!$E$6
Name SelectedRelicID: Variables!$B$5
Name Tbl_EffectParam: EffectParam!$A$2:$D$2080
Name PoolId3: Variables!$B$14
Name SelectedEffect_2: Variables!$B$7
Name SelectedCurse_1: Variables!$B$9
Name Tbl_EffectSource: Tables!$E$2:$G$5
Name HANDLE_EMPTY_POOL: LAMBDA(pool_id_x, lambda_pool, if(pool_id_x<>-1 ,lambda_pool,"Empty"))
Name GET_LANGUAGE_COL: LAMBDA(rng, lang_cell, match(lang_cell,CHOOSEROWS(offset(rng,-1,0),1),0))
Name UNFILTERED_POOL: LAMBDA(pool_id_x, choosecols(filter(Tbl_PoolParam, CHOOSECOLS(Tbl_PoolParam,1) =pool_id_x),2))

Sheet UI
A1: =HLOOKUP($B$1,Tbl_Translation[#ALL],ROW()+1,false) -> Language | B1: English | D1: =HLOOKUP($B$1,Tbl_Translation[#ALL],10,false) -> Final Result | E1: ID | F1: =HLOOKUP($B$1,Tbl_Translation[#ALL],11,false) -> Name / Effect Description
A2: =HLOOKUP($B$1,Tbl_Translation[#ALL],ROW()+1,false) -> Relic | B2: 102 - Grand Burning Scene (Red) | D2: =HLOOKUP($B$1,Tbl_Translation[#ALL],ROW()+1,false) -> Relic | E2: =SelectedRelicID -> 102 | F2: =iferror(TRIM(mid(UI!B2,SEARCH("-",UI!B2)+2,LEN(B2))), "Empty") -> Grand Burning Scene (Red)
A3: =HLOOKUP($B$1,Tbl_Translation[#ALL],ROW()+1,false) -> Attach Effect 1 | B3: 7000100-Mind +1 | D3: =HLOOKUP($B$1,Tbl_Translation[#ALL],ROW()+1,false) -> Attach Effect 1 | E3: {=SORT(Variables!B6:B8,Variables!H6:H8,true,Variables!B6:B8,true)} -> 7000000 | F3: =if(E3=EmptyID,"Empty",vlookup(VLOOKUP(value(E3),Tbl_EffectParam,GET_LANGUAGE_COL(Tbl_EffectParam,"attachTextId")),Tbl_EffectName,GET_LANGUAGE_COL(Tbl_EffectName, $B$1),false)) -> Vigor +1
A4: =HLOOKUP($B$1,Tbl_Translation[#ALL],ROW()+1,false) -> Attach Effect 2 | B4: 7000000-Vigor +1 | D4: =HLOOKUP($B$1,Tbl_Translation[#ALL],ROW()+1,false) -> Attach Effect 2 | E4: 7000100 | F4: =if(E4=EmptyID,"Empty",vlookup(VLOOKUP(value(E4),Tbl_EffectParam,GET_LANGUAGE_COL(Tbl_EffectParam,"attachTextId")),Tbl_EffectName,GET_LANGUAGE_COL(Tbl_EffectName, $B$1),false)) -> Mind +1
A5: =HLOOKUP($B$1,Tbl_Translation[#ALL],ROW()+1,false) -> Attach Effect 3 | B5: 7000500-Intelligence +1 | D5: =HLOOKUP($B$1,Tbl_Translation[#ALL],ROW()+1,false) -> Attach Effect 3 | E5: 7000500 | F5: =if(E5=EmptyID,"Empty",vlookup(VLOOKUP(value(E5),Tbl_EffectParam,GET_LANGUAGE_COL(Tbl_EffectParam,"attachTextId")),Tbl_EffectName,GET_LANGUAGE_COL(Tbl_EffectName, $B$1),false)) -> Intelligence +1
A6: =HLOOKUP($B$1,Tbl_Translation[#ALL],ROW()+1,false) -> Curse Effect 1 | B6: Empty | D6: =HLOOKUP($B$1,Tbl_Translation[#ALL],ROW()+1,false) -> Curse Effect 1 | E6: {=SORT(Variables!B9:B11,Variables!H9:H11,true,Variables!B9:B11,true)} -> 4294967295 | F6: =if(E6=EmptyID,"Empty",vlookup(VLOOKUP(value(E6),Tbl_EffectParam,GET_LANGUAGE_COL(Tbl_EffectParam,"attachTextId")),Tbl_EffectName,GET_LANGUAGE_COL(Tbl_EffectName, $B$1),false)) -> Empty
A7: =HLOOKUP($B$1,Tbl_Translation[#ALL],ROW()+1,false) -> Curse Effect 2 | B7: Empty | D7: =HLOOKUP($B$1,Tbl_Translation[#ALL],ROW()+1,false) -> Curse Effect 2 | E7: 4294967295 | F7: =if(E7=EmptyID,"Empty",vlookup(VLOOKUP(value(E7),Tbl_EffectParam,GET_LANGUAGE_COL(Tbl_EffectParam,"attachTextId")),Tbl_EffectName,GET_LANGUAGE_COL(Tbl_EffectName, $B$1),false)) -> Empty
A8: =HLOOKUP($B$1,Tbl_Translation[#ALL],ROW()+1,false) -> Curse Effect 3 | B8: Empty | D8: =HLOOKUP($B$1,Tbl_Translation[#ALL],ROW()+1,false) -> Curse Effect 3 | E8: 4294967295 | F8: =if(E8=EmptyID,"Empty",vlookup(VLOOKUP(value(E8),Tbl_EffectParam,GET_LANGUAGE_COL(Tbl_EffectParam,"attachTextId")),Tbl_EffectName,GET_LANGUAGE_COL(Tbl_EffectName, $B$1),false)) -> Empty

Sheet Translation
A1: English | B1: 繁體中文 | C1: 简体中文
A2: Language | B2: 語言 | C2: 语言
A3: Relic | B3: 遺物 | C3: 遗物
A4: Attach Effect 1 | B4: 效果1 | C4: 效果1
A5: Attach Effect 2 | B5: 效果2 | C5: 效果2
A6: Attach Effect 3 | B6: 效果3 | C6: 效果3
A7: Curse Effect 1 | B7: 詛咒1 | C7: 诅咒1
A8: Curse Effect 2 | B8: 詛咒2 | C8: 诅咒2
A9: Curse Effect 3 | B9: 詛咒3 | C9: 诅咒3
A10: Final Result | B10: 最終結果 | C10: 最终结果
A11: Name / Effect Description | B11: 名稱 / 效果描述 | C11: 名称 / 效果描述

Sheet Variables
A1: Empty ID | B1: 4294967295
A2: AttachEffectParam URL | B2: https://raw.githubusercontent.com/ip1259/Elden-Ring-Nightreign-Legal-Relic-Generator/refs/heads/main/AttachEffectParam.csv
A3: EffectPool URL | B3: https://raw.githubusercontent.com/ip1259/Elden-Ring-Nightreign-Legal-Relic-Generator/refs/heads/main/AttachEffectTableParam.csv
A4: AntiqueParam URL | B4: https://raw.githubusercontent.com/ip1259/Elden-Ring-Nightreign-Legal-Relic-Generator/refs/heads/main/EquipParamAntique.csv
A5: selected relic id | B5: =iferror(TRIM(LEFT(UI!B2,SEARCH("-",UI!B2)-1)), EmptyID) -> 102
A6: selected effect 1 id | B6: =iferror(TRIM(LEFT(UI!B3,SEARCH("-",UI!B3)-1)), EmptyID) -> 7000100 | D6: Conflic ID 1 | E6: {=if(SelectedEffect_1=EmptyID,-1,vlookup(Value(SelectedEffect_1),Tbl_EffectParam,Match("compatibilityId", chooseRows(offset(Tbl_EffectParam,-1,0),1),0),false))} -> 7000100 | G6: override ID 1 | H6: {=if(SelectedEffect_1=EmptyID,9999999999,vlookup(Value(SelectedEffect_1),Tbl_EffectParam,Match("overrideEffectId", chooseRows(offset(Tbl_EffectParam,-1,0),1),0),false))} -> 1000
A7: selected effect 2 id | B7: =iferror(TRIM(LEFT(UI!B4,SEARCH("-",UI!B4)-1)), EmptyID) -> 7000000 | D7: Conflic ID 2 | E7: {=if(SelectedEffect_2=EmptyID,-1,vlookup(Value(SelectedEffect_2),Tbl_EffectParam,Match("compatibilityId", chooseRows(offset(Tbl_EffectParam,-1,0),1),0),false))} -> 7000000 | G7: override ID 2 | H7: {=if(SelectedEffect_2=EmptyID,9999999999,vlookup(Value(SelectedEffect_2),Tbl_EffectParam,Match("overrideEffectId", chooseRows(offset(Tbl_EffectParam,-1,0),1),0),false))} -> 1000
A8: selected effect 3 id | B8: =iferror(TRIM(LEFT(UI!B5,SEARCH("-",UI!B5)-1)), EmptyID) -> 7000500 | D8: Conflic ID 3 | E8: {=if(SelectedEffect_3=EmptyID,-1,vlookup(Value(SelectedEffect_3),Tbl_EffectParam,Match("compatibilityId", chooseRows(offset(Tbl_EffectParam,-1,0),1),0),false))} -> 7000500 | G8: override ID 3 | H8: {=if(SelectedEffect_3=EmptyID,9999999999,vlookup(Value(SelectedEffect_3),Tbl_EffectParam,Match("overrideEffectId", chooseRows(offset(Tbl_EffectParam,-1,0),1),0),false))} -> 1000
A9: selected cuese 1 id | B9: =iferror(TRIM(LEFT(UI!B6,SEARCH("-",UI!B6)-1)), EmptyID) -> 4294967295 | D9: Conflic ID 4 | E9: {=if(SelectedCurse_1=EmptyID,-1,vlookup(Value(SelectedCurse_1),Tbl_EffectParam,Match("compatibilityId", chooseRows(offset(Tbl_EffectParam,-1,0),1),0),false))} -> -1 | G9: override ID 4 | H9: {=if(SelectedCurse_1=EmptyID,9999999999,vlookup(Value(SelectedCurse_1),Tbl_EffectParam,Match("overrideEffectId", chooseRows(offset(Tbl_EffectParam,-1,0),1),0),false))} -> 9999999999
A10: selected cuese 2 id | B10: =iferror(TRIM(LEFT(UI!B7,SEARCH("-",UI!B7)-1)), EmptyID) -> 4294967295 | D10: Conflic ID 5 | E10: {=if(SelectedCurse_2=EmptyID,-1,vlookup(Value(SelectedCurse_2),Tbl_EffectParam,Match("compatibilityId", chooseRows(offset(Tbl_EffectParam,-1,0),1),0),false))} -> -1 | G10: override ID 5 | H10: {=if(SelectedCurse_2=EmptyID,9999999999,vlookup(Value(SelectedCurse_2),Tbl_EffectParam,Match("overrideEffectId", chooseRows(offset(Tbl_EffectParam,-1,0),1),0),false))} -> 9999999999
A11: selected cuese 3 id | B11: =iferror(TRIM(LEFT(UI!B8,SEARCH("-",UI!B8)-1)), EmptyID) -> 4294967295 | D11: Conflic ID 6 | E11: {=if(SelectedCurse_3=EmptyID,-1,vlookup(Value(SelectedCurse_3),Tbl_EffectParam,Match("compatibilityId", chooseRows(offset(Tbl_EffectParam,-1,0),1),0),false))} -> -1 | G11: override ID 6 | H11: {=if(SelectedCurse_3=EmptyID,9999999999,vlookup(Value(SelectedCurse_3),Tbl_EffectParam,Match("overrideEffectId", chooseRows(offset(Tbl_EffectParam,-1,0),1),0),false))} -> 9999999999
A12: pool 1 id | B12: {=iferror(vlookup(Value(SelectedRelicID),Tbl_RelicParam,Match("attachEffectTableId_1", chooseRows(offset(Tbl_RelicParam,-1,0),1),0),false),-1)} -> 300
A13: pool 2 id | B13: {=iferror(vlookup(Value(SelectedRelicID),Tbl_RelicParam,Match("attachEffectTableId_2", chooseRows(offset(Tbl_RelicParam,-1,0),1),0),false),-1)} -> 200
A14: pool 3 id | B14: {=iferror(vlookup(Value(SelectedRelicID),Tbl_RelicParam,Match("attachEffectTableId_3", chooseRows(offset(Tbl_RelicParam,-1,0),1),0),false),-1)} -> 100
A15: pool 4 id | B15: {=iferror(vlookup(Value(SelectedRelicID),Tbl_RelicParam,Match("attachEffectTableId_curse1", chooseRows(offset(Tbl_RelicParam,-1,0),1),0),false),-1)} -> -1
A16: pool 5 id | B16: {=iferror(vlookup(Value(SelectedRelicID),Tbl_RelicParam,Match("attachEffectTableId_curse2", chooseRows(offset(Tbl_RelicParam,-1,0),1),0),false),-1)} -> -1
A17: pool 6 id | B17: {=iferror(vlookup(Value(SelectedRelicID),Tbl_RelicParam,Match("attachEffectTableId_curse3", chooseRows(offset(Tbl_RelicParam,-1,0),1),0),false),-1)} -> -1

Sheet Lists
A1: Language
A2: {=TRANSPOSE(CHOOSEROWS(Tbl_Translation[#ALL],1))} -> English
A3: 繁體中文
A4: 简体中文

Sheet Tables
A1: Lang | B1: Url | C1: Title | E1: Lang | F1: Url | G1: Title | I1: ID | J1: English | K1: 繁體中文 | L1: 简体中文
A2: en | B2: https://raw.githubusercontent.com/ip1259/Elden-Ring-Nightreign-Legal-Relic-Generator/refs/heads/main/en/AntiqueName.fmg.xml | C2: English | E2: en | F2: https://raw.githubusercontent.com/ip1259/Elden-Ring-Nightreign-Legal-Relic-Generator/refs/heads/main/en/AttachEffectName.fmg.xml | G2: English | I2: 0 | J2: Red | K2: 紅 | L2: 红
A3: en | B3: https://raw.githubusercontent.com/ip1259/Elden-Ring-Nightreign-Legal-Relic-Generator/refs/heads/main/en/AntiqueName_dlc01.fmg.xml | C3: English | E3: en | F3: https://raw.githubusercontent.com/ip1259/Elden-Ring-Nightreign-Legal-Relic-Generator/refs/heads/main/en/AttachEffectName_dlc01.fmg.xml | G3: English | I3: 1 | J3: Blue | K3: 藍 | L3: 蓝
A4: zh_tw | B4: https://raw.githubusercontent.com/ip1259/Elden-Ring-Nightreign-Legal-Relic-Generator/refs/heads/main/tcht/AntiqueName.fmg.xml | C4: 繁體中文 | E4: zh_tw | F4: https://raw.githubusercontent.com/ip1259/Elden-Ring-Nightreign-Legal-Relic-Generator/refs/heads/main/tcht/AttachEffectName.fmg.xml | G4: 繁體中文 | I4: 2 | J4: Yellow | K4: 黃 | L4: 黄
A5: zh_tw | B5: https://raw.githubusercontent.com/ip1259/Elden-Ring-Nightreign-Legal-Relic-Generator/refs/heads/main/tcht/AntiqueName_dlc01.fmg.xml | C5: 繁體中文 | E5: zh_tw | F5: https://raw.githubusercontent.com/ip1259/Elden-Ring-Nightreign-Legal-Relic-Generator/refs/heads/main/tcht/AttachEffectName_dlc01.fmg.xml | G5: 繁體中文 | I5: 3 | J5: Green | K5: 綠 | L5: 绿

Sheet Dynamic Tables
A1: RelicID | B1: Relic Name | C1: Relic Color | D1: Full Relic Display | F1: =IFERROR(__xludf.DUMMYFUNCTION("if(M2<>""Empty"",MAP(FILTER(M2:M2000, M2:M2000 <> """"), LAMBDA(cur,cur& ""-"" & vlookup(vlookup(cur,Tbl_EffectParam,MATCH(""attachTextId"",CHOOSEROWS(offset(Tbl_EffectParam,-1,0),1),0),false),Tbl_EffectName,match(UI!$B$1,Lst_Language[Language],0)+1,false"&"))),""Empty"")"),"7000000-Vigor +1") -> 7000000-Vigor +1 | G1: =IFERROR(__xludf.DUMMYFUNCTION("if(N2<>""Empty"",MAP(FILTER(N2:N2000, N2:N2000 <> """"), LAMBDA(cur,cur& ""-"" & vlookup(vlookup(cur,Tbl_EffectParam,MATCH(""attachTextId"",CHOOSEROWS(offset(Tbl_EffectParam,-1,0),1),0),false),Tbl_EffectName,match(UI!$B$1,Lst_Language[Language],0)+1,false"&"))),""Empty"")"),"7000000-Vigor +1") -> 7000000-Vigor +1 | H1: =IFERROR(__xludf.DUMMYFUNCTION("if(O2<>""Empty"",MAP(FILTER(O2:O2000, O2:O2000 <> """"), LAMBDA(cur,cur& ""-"" & vlookup(vlookup(cur,Tbl_EffectParam,MATCH(""attachTextId"",CHOOSEROWS(offset(Tbl_EffectParam,-1,0),1),0),false),Tbl_EffectName,match(UI!$B$1,Lst_Language[Language],0)+1,false"&"))),""Empty"")"),"7000200-Endurance +1") -> 7000200-Endurance +1 | I1: =IFERROR(__xludf.DUMMYFUNCTION("if(P2<>""Empty"",MAP(FILTER(P2:P2000, P2:P2000 <> """"), LAMBDA(cur,cur& ""-"" & vlookup(vlookup(cur,Tbl_EffectParam,MATCH(""attachTextId"",CHOOSEROWS(offset(Tbl_EffectParam,-1,0),1),0),false),Tbl_EffectName,match(UI!$B$1,Lst_Language[Language],0)+1,false"&"))),""Empty"")"),"Empty") -> Empty | J1: =IFERROR(__xludf.DUMMYFUNCTION("if(Q2<>""Empty"",MAP(FILTER(Q2:Q2000, Q2:Q2000 <> """"), LAMBDA(cur,cur& ""-"" & vlookup(vlookup(cur,Tbl_EffectParam,MATCH(""attachTextId"",CHOOSEROWS(offset(Tbl_EffectParam,-1,0),1),0),false),Tbl_EffectName,match(UI!$B$1,Lst_Language[Language],0)+1,false"&"))),""Empty"")"),"Empty") -> Empty | K1: =IFERROR(__xludf.DUMMYFUNCTION("if(R2<>""Empty"",MAP(FILTER(R2:R2000, R2:R2000 <> """"), LAMBDA(cur,cur& ""-"" & vlookup(vlookup(cur,Tbl_EffectParam,MATCH(""attachTextId"",CHOOSEROWS(offset(Tbl_EffectParam,-1,0),1),0),false),Tbl_EffectName,match(UI!$B$1,Lst_Language[Language],0)+1,false"&"))),""Empty"")"),"Empty") -> Empty | M1: Pool 1 | N1: Pool 2 | O1: Pool 3 | P1: CPool 1 | Q1: CPool 2 | R1: CPool 3
A2: {=CHOOSECOLS(Tbl_RelicParam,1)} -> 1 | B2: {=MAP(A2:A41714, LAMBDA(row, ifna(IF(row="", , VLOOKUP(row, Tbl_ItemName, GET_LANGUAGE_COL(Tbl_ItemName,UI!$B$1), FALSE)),"Unset")))} -> Antique | C2: {=CHOOSECOLS(Tbl_RelicParam,MATCH("relicColor",CHOOSEROWS(offset(Tbl_RelicParam,-1,0),1),0))} -> 0 | D2: =A2 & " - " & B2 & " (" & VLOOKUP(C2, Tbl_ColorMap[],2,false) & ")" -> 1 - Antique (Red) | F2: =IFERROR(__xludf.DUMMYFUNCTION("""COMPUTED_VALUE"""),"7000001-Vigor +2") -> 7000001-Vigor +2 | G2: =IFERROR(__xludf.DUMMYFUNCTION("""COMPUTED_VALUE"""),"7000001-Vigor +2") -> 7000001-Vigor +2 | H2: =IFERROR(__xludf.DUMMYFUNCTION("""COMPUTED_VALUE"""),"7000201-Endurance +2") -> 7000201-Endurance +2 | M2: =HANDLE_EMPTY_POOL(PoolId1, UNFILTERED_POOL(PoolId1)) -> 7000000 | N2: =HANDLE_EMPTY_POOL(PoolId2,SINGLE_CONFLICT_FILTER(PoolId2,SelectedEffect_1,ConfilctID1)) -> 7000000 | O2: =HANDLE_EMPTY_POOL(PoolId3, DOUBLE_CONFLICT_FILTER(PoolId3,SelectedEffect_1,SelectedEffect_2,ConfilctID1,ConflictID2)) -> 7000200 | P2: =HANDLE_EMPTY_POOL(PoolId4, UNFILTERED_POOL(PoolId4)) -> Empty | Q2: =HANDLE_EMPTY_POOL(PoolId5,SINGLE_CONFLICT_FILTER(PoolId5,SelectedCurse_1,ConflictID4)) -> Empty | R2: =HANDLE_EMPTY_POOL(PoolId6, DOUBLE_CONFLICT_FILTER(PoolId6,SelectedCurse_1,SelectedCurse_2,ConflictID4,ConflictID5)) -> Empty
A3: 2 | B3: Antique | C3: 0 | D3: =A3 & " - " & B3 & " (" & VLOOKUP(C3, Tbl_ColorMap[],2,false) & ")" -> 2 - Antique (Red) | F3: =IFERROR(__xludf.DUMMYFUNCTION("""COMPUTED_VALUE"""),"7000002-Vigor +3") -> 7000002-Vigor +3 | G3: =IFERROR(__xludf.DUMMYFUNCTION("""COMPUTED_VALUE"""),"7000002-Vigor +3") -> 7000002-Vigor +3 | H3: =IFERROR(__xludf.DUMMYFUNCTION("""COMPUTED_VALUE"""),"7000202-Endurance +3") -> 7000202-Endurance +3 | M3: 7000001 | N3: 7000001 | O3: 7000201
A4: 3 | B4: Antique | C4: 0 | D4: =A4 & " - " & B4 & " (" & VLOOKUP(C4, Tbl_ColorMap[],2,false) & ")" -> 3 - Antique (Red) | F4: =IFERROR(__xludf.DUMMYFUNCTION("""COMPUTED_VALUE"""),"7000100-Mind +1") -> 7000100-Mind +1 | G4: =IFERROR(__xludf.DUMMYFUNCTION("""COMPUTED_VALUE"""),"7000200-Endurance +1") -> 7000200-Endurance +1 | H4: =IFERROR(__xludf.DUMMYFUNCTION("""COMPUTED_VALUE"""),"7000300-Strength +1") -> 7000300-Strength +1 | M4: 7000002 | N4: 7000002 | O4: 7000202
A5: 4 | B5: Antique | C5: 0 | D5: =A5 & " - " & B5 & " (" & VLOOKUP(C5, Tbl_ColorMap[],2,false) & ")" -> 4 - Antique (Red) | F5: =IFERROR(__xludf.DUMMYFUNCTION("""COMPUTED_VALUE"""),"7000101-Mind +2") -> 7000101-Mind +2 | G5: =IFERROR(__xludf.DUMMYFUNCTION("""COMPUTED_VALUE"""),"7000201-Endurance +2") -> 7000201-Endurance +2 | H5: =IFERROR(__xludf.DUMMYFUNCTION("""COMPUTED_VALUE"""),"7000301-Strength +2") -> 7000301-Strength +2 | M5: 7000100 | N5: 7000200 | O5: 7000300
A6: 5 | B6: Antique | C6: 0 | D6: =A6 & " - " & B6 & " (" & VLOOKUP(C6, Tbl_ColorMap[],2,false) & ")" -> 5 - Antique (Red) | F6: =IFERROR(__xludf.DUMMYFUNCTION("""COMPUTED_VALUE"""),"7000102-Mind +3") -> 7000102-Mind +3 | G6: =IFERROR(__xludf.DUMMYFUNCTION("""COMPUTED_VALUE"""),"7000202-Endurance +3") -> 7000202-Endurance +3 | H6: =IFERROR(__xludf.DUMMYFUNCTION("""COMPUTED_VALUE"""),"7000302-Strength +3") -> 7000302-Strength +3 | M6: 7000101 | N6: 7000201 | O6: 7000301
A7: 6 | B7: Antique | C7: 0 | D7: =A7 & " - " & B7 & " (" & VLOOKUP(C7, Tbl_ColorMap[],2,false) & ")" -> 6 - Antique (Red) | F7: =IFERROR(__xludf.DUMMYFUNCTION("""COMPUTED_VALUE"""),"7000200-Endurance +1") -> 7000200-Endurance +1 | G7: =IFERROR(__xludf.DUMMYFUNCTION("""COMPUTED_VALUE"""),"7000300-Strength +1") -> 7000300-Strength +1 | H7: =IFERROR(__xludf.DUMMYFUNCTION("""COMPUTED_VALUE"""),"7000400-Dexterity +1") -> 7000400-Dexterity +1 | M7: 7000102 | N7: 7000202 | O7: 7000302
A8: 10 | B8: Murk | C8: 0 | D8: =A8 & " - " & B8 & " (" & VLOOKUP(C8, Tbl_ColorMap[],2,false) & ")" -> 10 - Murk (Red) | F8: =IFERROR(__xludf.DUMMYFUNCTION("""COMPUTED_VALUE"""),"7000201-Endurance +2") -> 7000201-Endurance +2 | G8: =IFERROR(__xludf.DUMMYFUNCTION("""COMPUTED_VALUE"""),"7000301-Strength +2") -> 7000301-Strength +2 | H8: =IFERROR(__xludf.DUMMYFUNCTION("""COMPUTED_VALUE"""),"7000401-Dexterity +2") -> 7000401-Dexterity +2 | M8: 7000200 | N8: 7000300 | O8: 7000400
A9: 11 | B9: Sovereign Sigil | C9: 0 | D9: =A9 & " - " & B9 & " (" & VLOOKUP(C9, Tbl_ColorMap[],2,false) & ")" -> 11 - Sovereign Sigil (Red) | F9: =IFERROR(__xludf.DUMMYFUNCTION("""COMPUTED_VALUE"""),"7000202-Endurance +3") -> 7000202-Endurance +3 | G9: =IFERROR(__xludf.DUMMYFUNCTION("""COMPUTED_VALUE"""),"7000302-Strength +3") -> 7000302-Strength +3 | H9: =IFERROR(__xludf.DUMMYFUNCTION("""COMPUTED_VALUE"""),"7000402-Dexterity +3") -> 7000402-Dexterity +3 | M9: 7000201 | N9: 7000301 | O9: 7000401
A10: 20 | B10: Scenic Flatstone | C10: 0 | D10: =A10 & " - " & B10 & " (" & VLOOKUP(C10, Tbl_ColorMap[],2,false) & ")" -> 20 - Scenic Flatstone (Red) | F10: =IFERROR(__xludf.DUMMYFUNCTION("""COMPUTED_VALUE"""),"7000300-Strength +1") -> 7000300-Strength +1 | G10: =IFERROR(__xludf.DUMMYFUNCTION("""COMPUTED_VALUE"""),"7000400-Dexterity +1") -> 7000400-Dexterity +1 | H10: =IFERROR(__xludf.DUMMYFUNCTION("""COMPUTED_VALUE"""),"7000500-Intelligence +1") -> 7000500-Intelligence +1 | M10: 7000202 | N10: 7000302 | O10: 7000402
A11: 100 | B11: Delicate Burning Scene | C11: 0 | D11: =A11 & " - " & B11 & " (" & VLOOKUP(C11, Tbl_ColorMap[],2,false) & ")" -> 100 - Delicate Burning Scene (Red) | F11: =IFERROR(__xludf.DUMMYFUNCTION("""COMPUTED_VALUE"""),"7000301-Strength +2") -> 7000301-Strength +2 | G11: =IFERROR(__xludf.DUMMYFUNCTION("""COMPUTED_VALUE"""),"7000401-Dexterity +2") -> 7000401-Dexterity +2 | H11: =IFERROR(__xludf.DUMMYFUNCTION("""COMPUTED_VALUE"""),"7000501-Intelligence +2") -> 7000501-Intelligence +2 | M11: 7000300 | N11: 7000400 | O11: 7000500
A12: 101 | B12: Polished Burning Scene | C12: 0 | D12: =A12 & " - " & B12 & " (" & VLOOKUP(C12, Tbl_ColorMap[],2,false) & ")" -> 101 - Polished Burning Scene (Red) | F12: =IFERROR(__xludf.DUMMYFUNCTION("""COMPUTED_VALUE"""),"7000302-Strength +3") -> 7000302-Strength +3 | G12: =IFERROR(__xludf.DUMMYFUNCTION("""COMPUTED_VALUE"""),"7000402-Dexterity +3") -> 7000402-Dexterity +3 | H12: =IFERROR(__xludf.DUMMYFUNCTION("""COMPUTED_VALUE"""),"7000502-Intelligence +3") -> 7000502-Intelligence +3 | M12: 7000301 | N12: 7000401 | O12: 7000501
A13: 102 | B13: Grand Burning Scene | C13: 0 | D13: =A13 & " - " & B13 & " (" & VLOOKUP(C13, Tbl_ColorMap[],2,false) & ")" -> 102 - Grand Burning Scene (Red) | F13: =IFERROR(__xludf.DUMMYFUNCTION("""COMPUTED_VALUE"""),"7000400-Dexterity +1") -> 7000400-Dexterity +1 | G13: =IFERROR(__xludf.DUMMYFUNCTION("""COMPUTED_VALUE"""),"7000500-Intelligence +1") -> 7000500-Intelligence +1 | H13: =IFERROR(__xludf.DUMMYFUNCTION("""COMPUTED_VALUE"""),"7000600-Faith +1") -> 7000600-Faith +1 | M13: 7000302 | N13: 7000402 | O13: 7000502
A14: 103 | B14: Delicate Burning Scene | C14: 0 | D14: =A14 & " - " & B14 & " (" & VLOOKUP(C14, Tbl_ColorMap[],2,false) & ")" -> 103 - Delicate Burning Scene (Red) | F14: =IFERROR(__xludf.DUMMYFUNCTION("""COMPUTED_VALUE"""),"7000401-Dexterity +2") -> 7000401-Dexterity +2 | G14: =IFERROR(__xludf.DUMMYFUNCTION("""COMPUTED_VALUE"""),"7000501-Intelligence +2") -> 7000501-Intelligence +2 | H14: =IFERROR(__xludf.DUMMYFUNCTION("""COMPUTED_VALUE"""),"7000601-Faith +2") -> 7000601-Faith +2 | M14: 7000400 | N14: 7000500 | O14: 7000600
A15: 104 | B15: Polished Burning Scene | C15: 0 | D15: =A15 & " - " & B15 & " (" & VLOOKUP(C15, Tbl_ColorMap[],2,false) & ")" -> 104 - Polished Burning Scene (Red) | F15: =IFERROR(__xludf.DUMMYFUNCTION("""COMPUTED_VALUE"""),"7000402-Dexterity +3") -> 7000402-Dexterity +3 | G15: =IFERROR(__xludf.DUMMYFUNCTION("""COMPUTED_VALUE"""),"7000502-Intelligence +3") -> 7000502-Intelligence +3 | H15: =IFERROR(__xludf.DUMMYFUNCTION("""COMPUTED_VALUE"""),"7000602-Faith +3") -> 7000602-Faith +3 | M15: 7000401 | N15: 7000501 | O15: 7000601
A16: 105 | B16: Grand Burning Scene | C16: 0 | D16: =A16 & " - " & B16 & " (" & VLOOKUP(C16, Tbl_ColorMap[],2,false) & ")" -> 105 - Grand Burning Scene (Red) | F16: =IFERROR(__xludf.DUMMYFUNCTION("""COMPUTED_VALUE"""),"7000500-Intelligence +1") -> 7000500-Intelligence +1 | G16: =IFERROR(__xludf.DUMMYFUNCTION("""COMPUTED_VALUE"""),"7000600-Faith +1") -> 7000600-Faith +1 | H16: =IFERROR(__xludf.DUMMYFUNCTION("""COMPUTED_VALUE"""),"7000700-Arcane +1") -> 7000700-Arcane +1 | M16: 7000402 | N16: 7000502 | O16: 7000602
A17: 106 | B17: Delicate Burning Scene | C17: 0 | D17: =A17 & " - " & B17 & " (" & VLOOKUP(C17, Tbl_ColorMap[],2,false) & ")" -> 106 - Delicate Burning Scene (Red) | F17: =IFERROR(__xludf.DUMMYFUNCTION("""COMPUTED_VALUE"""),"7000501-Intelligence +2") -> 7000501-Intelligence +2 | G17: =IFERROR(__xludf.DUMMYFUNCTION("""COMPUTED_VALUE"""),"7000601-Faith +2") -> 7000601-Faith +2 | H17: =IFERROR(__xludf.DUMMYFUNCTION("""COMPUTED_VALUE"""),"7000701-Arcane +2") -> 7000701-Arcane +2 | M17: 7000500 | N17: 7000600 | O17: 7000700
A18: 107 | B18: Polished Burning Scene | C18: 0 | D18: =A18 & " - " & B18 & " (" & VLOOKUP(C18, Tbl_ColorMap[],2,false) & ")" -> 107 - Polished Burning Scene (Red) | F18: =IFERROR(__xludf.DUMMYFUNCTION("""COMPUTED_VALUE"""),"7000502-Intelligence +3") -> 7000502-Intelligence +3 | G18: =IFERROR(__xludf.DUMMYFUNCTION("""COMPUTED_VALUE"""),"7000602-Faith +3") -> 7000602-Faith +3 | H18: =IFERROR(__xludf.DUMMYFUNCTION("""COMPUTED_VALUE"""),"7000702-Arcane +3") -> 7000702-Arcane +3 | M18: 7000501 | N18: 7000601 | O18: 7000701
A19: 108 | B19: Grand Burning Scene | C19: 0 | D19: =A19 & " - " & B19 & " (" & VLOOKUP(C19, Tbl_ColorMap[],2,false) & ")" -> 108 - Grand Burning Scene (Red) | F19: =IFERROR(__xludf.DUMMYFUNCTION("""COMPUTED_VALUE"""),"7000600-Faith +1") -> 7000600-Faith +1 | G19: =IFERROR(__xludf.DUMMYFUNCTION("""COMPUTED_VALUE"""),"7000700-Arcane +1") -> 7000700-Arcane +1 | H19: =IFERROR(__xludf.DUMMYFUNCTION("""COMPUTED_VALUE"""),"7000800-Character Skill Cooldown Reduction +1") -> 7000800-Character Skill Cooldown Reduction +1 | M19: 7000502 | N19: 7000602 | O19: 7000702
A20: 109 | B20: Delicate Drizzly Scene | C20: 1 | D20: =A20 & " - " & B20 & " (" & VLOOKUP(C20, Tbl_ColorMap[],2,false) & ")" -> 109 - Delicate Drizzly Scene (Blue) | F20: =IFERROR(__xludf.DUMMYFUNCTION("""COMPUTED_VALUE"""),"7000601-Faith +2") -> 7000601-Faith +2 | G20: =IFERROR(__xludf.DUMMYFUNCTION("""COMPUTED_VALUE"""),"7000701-Arcane +2") -> 7000701-Arcane +2 | H20: =IFERROR(__xludf.DUMMYFUNCTION("""COMPUTED_VALUE"""),"7000801-Character Skill Cooldown Reduction +2") -> 7000801-Character Skill Cooldown Reduction +2 | M20: 7000600 | N20: 7000700 | O20: 7000800
A21: 110 | B21: Polished Drizzly Scene | C21: 1 | D21: =A21 & " - " & B21 & " (" & VLOOKUP(C21, Tbl_ColorMap[],2,false) & ")" -> 110 - Polished Drizzly Scene (Blue) | F21: =IFERROR(__xludf.DUMMYFUNCTION("""COMPUTED_VALUE"""),"7000602-Faith +3") -> 7000602-Faith +3 | G21: =IFERROR(__xludf.DUMMYFUNCTION("""COMPUTED_VALUE"""),"7000702-Arcane +3") -> 7000702-Arcane +3 | H21: =IFERROR(__xludf.DUMMYFUNCTION("""COMPUTED_VALUE"""),"7000802-Character Skill Cooldown Reduction +3") -> 7000802-Character Skill Cooldown Reduction +3 | M21: 7000601 | N21: 7000701 | O21: 7000801
A22: 111 | B22: Grand Drizzly Scene | C22: 1 | D22: =A22 & " - " & B22 & " (" & VLOOKUP(C22, Tbl_ColorMap[],2,false) & ")" -> 111 - Grand Drizzly Scene (Blue) | F22: =IFERROR(__xludf.DUMMYFUNCTION("""COMPUTED_VALUE"""),"7000700-Arcane +1") -> 7000700-Arcane +1 | G22: =IFERROR(__xludf.DUMMYFUNCTION("""COMPUTED_VALUE"""),"7000800-Character Skill Cooldown Reduction +1") -> 7000800-Character Skill Cooldown Reduction +1 | H22: =IFERROR(__xludf.DUMMYFUNCTION("""COMPUTED_VALUE"""),"7000900-Ultimate Art Auto Charge +1") -> 7000900-Ultimate Art Auto Charge +1 | M22: 7000602 | N22: 7000702 | O22: 7000802
A23: 112 | B23: Delicate Drizzly Scene | C23: 1 | D23: =A23 & " - " & B23 & " (" & VLOOKUP(C23, Tbl_ColorMap[],2,false) & ")" -> 112 - Delicate Drizzly Scene (Blue) | F23: =IFERROR(__xludf.DUMMYFUNCTION("""COMPUTED_VALUE"""),"7000701-Arcane +2") -> 7000701-Arcane +2 | G23: =IFERROR(__xludf.DUMMYFUNCTION("""COMPUTED_VALUE"""),"7000801-Character Skill Cooldown Reduction +2") -> 7000801-Character Skill Cooldown Reduction +2 | H23: =IFERROR(__xludf.DUMMYFUNCTION("""COMPUTED_VALUE"""),"7000901-Ultimate Art Auto Charge +2") -> 7000901-Ultimate Art Auto Charge +2 | M23: 7000700 | N23: 7000800 | O23: 7000900
A24: 113 | B24: Polished Drizzly Scene | C24: 1 | D24: =A24 & " - " & B24 & " (" & VLOOKUP(C24, Tbl_ColorMap[],2,false) & ")" -> 113 - Polished Drizzly Scene (Blue) | F24: =IFERROR(__xludf.DUMMYFUNCTION("""COMPUTED_VALUE"""),"7000702-Arcane +3") -> 7000702-Arcane +3 | G24: =IFERROR(__xludf.DUMMYFUNCTION("""COMPUTED_VALUE"""),"7000802-Character Skill Cooldown Reduction +3") -> 7000802-Character Skill Cooldown Reduction +3 | H24: =IFERROR(__xludf.DUMMYFUNCTION("""COMPUTED_VALUE"""),"7000902-Ultimate Art Auto Charge +3") -> 7000902-Ultimate Art Auto Charge +3 | M24: 7000701 | N24: 7000801 | O24: 7000901
A25: 114 | B25: Grand Drizzly Scene | C25: 1 | D25: =A25 & " - " & B25 & " (" & VLOOKUP(C25, Tbl_ColorMap[],2,false) & ")" -> 114 - Grand Drizzly Scene (Blue) | F25: =IFERROR(__xludf.DUMMYFUNCTION("""COMPUTED_VALUE"""),"7000800-Character Skill Cooldown Reduction +1") -> 7000800-Character Skill Cooldown Reduction +1 | G25: =IFERROR(__xludf.DUMMYFUNCTION("""COMPUTED_VALUE"""),"7000900-Ultimate Art Auto Charge +1") -> 7000900-Ultimate Art Auto Charge +1 | H25: =IFERROR(__xludf.DUMMYFUNCTION("""COMPUTED_VALUE"""),"7001000-Poise +1") -> 7001000-Poise +1 | M25: 7000702 | N25: 7000802 | O25: 7000902
A26: 115 | B26: Delicate Drizzly Scene | C26: 1 | D26: =A26 & " - " & B26 & " (" & VLOOKUP(C26, Tbl_ColorMap[],2,false) & ")" -> 115 - Delicate Drizzly Scene (Blue) | F26: =IFERROR(__xludf.DUMMYFUNCTION("""COMPUTED_VALUE"""),"7000801-Character Skill Cooldown Reduction +2") -> 7000801-Character Skill Cooldown Reduction +2 | G26: =IFERROR(__xludf.DUMMYFUNCTION("""COMPUTED_VALUE"""),"7000901-Ultimate Art Auto Charge +2") -> 7000901-Ultimate Art Auto Charge +2 | H26: =IFERROR(__xludf.DUMMYFUNCTION("""COMPUTED_VALUE"""),"7001001-Poise +2") -> 7001001-Poise +2 | M26: 7000800 | N26: 7000900 | O26: 7001000
A27: 116 | B27: Polished Drizzly Scene | C27: 1 | D27: =A27 & " - " & B27 & " (" & VLOOKUP(C27, Tbl_ColorMap[],2,false) & ")" -> 116 - Polished Drizzly Scene (Blue) | F27: =IFERROR(__xludf.DUMMYFUNCTION("""COMPUTED_VALUE"""),"7000802-Character Skill Cooldown Reduction +3") -> 7000802-Character Skill Cooldown Reduction +3 | G27: =IFERROR(__xludf.DUMMYFUNCTION("""COMPUTED_VALUE"""),"7000902-Ultimate Art Auto Charge +3") -> 7000902-Ultimate Art Auto Charge +3 | H27: =IFERROR(__xludf.DUMMYFUNCTION("""COMPUTED_VALUE"""),"7001002-Poise +3") -> 7001002-Poise +3 | M27: 7000801 | N27: 7000901 | O27: 7001001
A28: 117 | B28: Grand Drizzly Scene | C28: 1 | D28: =A28 & " - " & B28 & " (" & VLOOKUP(C28, Tbl_ColorMap[],2,false) & ")" -> 117 - Grand Drizzly Scene (Blue) | F28: =IFERROR(__xludf.DUMMYFUNCTION("""COMPUTED_VALUE"""),"7000900-Ultimate Art Auto Charge +1") -> 7000900-Ultimate Art Auto Charge +1 | G28: =IFERROR(__xludf.DUMMYFUNCTION("""COMPUTED_VALUE"""),"7001000-Poise +1") -> 7001000-Poise +1 | H28: =IFERROR(__xludf.DUMMYFUNCTION("""COMPUTED_VALUE"""),"7001400-Physical Attack Up") -> 7001400-Physical Attack Up | M28: 7000802 | N28: 7000902 | O28: 7001002
A29: 118 | B29: Delicate Luminous Scene | C29: 2 | D29: =A29 & " - " & B29 & " (" & VLOOKUP(C29, Tbl_ColorMap[],2,false) & ")" -> 118 - Delicate Luminous Scene (Yellow) | F29: =IFERROR(__xludf.DUMMYFUNCTION("""COMPUTED_VALUE"""),"7000901-Ultimate Art Auto Charge +2") -> 7000901-Ultimate Art Auto Charge +2 | G29: =IFERROR(__xludf.DUMMYFUNCTION("""COMPUTED_VALUE"""),"7001001-Poise +2") -> 7001001-Poise +2 | H29: =IFERROR(__xludf.DUMMYFUNCTION("""COMPUTED_VALUE"""),"7001401-Physical Attack Up +1") -> 7001401-Physical Attack Up +1 | M29: 7000900 | N29: 7001000 | O29: 7001400
A30: 119 | B30: Polished Luminous Scene | C30: 2 | D30: =A30 & " - " & B30 & " (" & VLOOKUP(C30, Tbl_ColorMap[],2,false) & ")" -> 119 - Polished Luminous Scene (Yellow) | F30: =IFERROR(__xludf.DUMMYFUNCTION("""COMPUTED_VALUE"""),"7000902-Ultimate Art Auto Charge +3") -> 7000902-Ultimate Art Auto Charge +3 | G30: =IFERROR(__xludf.DUMMYFUNCTION("""COMPUTED_VALUE"""),"7001002-Poise +3") -> 7001002-Poise +3 | H30: =IFERROR(__xludf.DUMMYFUNCTION("""COMPUTED_VALUE"""),"7001402-Physical Attack Up +2") -> 7001402-Physical Attack Up +2 | M30: 7000901 | N30: 7001001 | O30: 7001401
A31: 120 | B31: Grand Luminous Scene | C31: 2 | D31: =A31 & " - " & B31 & " (" & VLOOKUP(C31, Tbl_ColorMap[],2,false) & ")" -> 120 - Grand Luminous Scene (Yellow) | F31: =IFERROR(__xludf.DUMMYFUNCTION("""COMPUTED_VALUE"""),"7001000-Poise +1") -> 7001000-Poise +1 | G31: =IFERROR(__xludf.DUMMYFUNCTION("""COMPUTED_VALUE"""),"7001400-Physical Attack Up") -> 7001400-Physical Attack Up | H31: =IFERROR(__xludf.DUMMYFUNCTION("""COMPUTED_VALUE"""),"7001500-Magic Attack Power Up") -> 7001500-Magic Attack Power Up | M31: 7000902 | N31: 7001002 | O31: 7001402
A32: 121 | B32: Delicate Luminous Scene | C32: 2 | D32: =A32 & " - " & B32 & " (" & VLOOKUP(C32, Tbl_ColorMap[],2,false) & ")" -> 121 - Delicate Luminous Scene (Yellow) | F32: =IFERROR(__xludf.DUMMYFUNCTION("""COMPUTED_VALUE"""),"7001001-Poise +2") -> 7001001-Poise +2 | G32: =IFERROR(__xludf.DUMMYFUNCTION("""COMPUTED_VALUE"""),"7001401-Physical Attack Up +1") -> 7001401-Physical Attack Up +1 | H32: =IFERROR(__xludf.DUMMYFUNCTION("""COMPUTED_VALUE"""),"7001501-Magic Attack Power Up +1") -> 7001501-Magic Attack Power Up +1 | M32: 7001000 | N32: 7001400 | O32: 7001500
A33: 122 | B33: Polished Luminous Scene | C33: 2 | D33: =A33 & " - " & B33 & " (" & VLOOKUP(C33, Tbl_ColorMap[],2,false) & ")" -> 122 - Polished Luminous Scene (Yellow) | F33: =IFERROR(__xludf.DUMMYFUNCTION("""COMPUTED_VALUE"""),"7001002-Poise +3") -> 7001002-Poise +3 | G33: =IFERROR(__xludf.DUMMYFUNCTION("""COMPUTED_VALUE"""),"7001402-Physical Attack Up +2") -> 7001402-Physical Attack Up +2 | H33: =IFERROR(__xludf.DUMMYFUNCTION("""COMPUTED_VALUE"""),"7001502-Magic Attack Power Up +2") -> 7001502-Magic Attack Power Up +2 | M33: 7001001 | N33: 7001401 | O33: 7001501
A34: 123 | B34: Grand Luminous Scene | C34: 2 | D34: =A34 & " - " & B34 & " (" & VLOOKUP(C34, Tbl_ColorMap[],2,false) & ")" -> 123 - Grand Luminous Scene (Yellow) | F34: =IFERROR(__xludf.DUMMYFUNCTION("""COMPUTED_VALUE"""),"7001400-Physical Attack Up") -> 7001400-Physical Attack Up | G34: =IFERROR(__xludf.DUMMYFUNCTION("""COMPUTED_VALUE"""),"7001500-Magic Attack Power Up") -> 7001500-Magic Attack Power Up | H34: =IFERROR(__xludf.DUMMYFUNCTION("""COMPUTED_VALUE"""),"7001600-Fire Attack Power Up") -> 7001600-Fire Attack Power Up | M34: 7001002 | N34: 7001402 | O34: 7001502
A35: 124 | B35: Delicate Luminous Scene | C35: 2 | D35: =A35 & " - " & B35 & " (" & VLOOKUP(C35, Tbl_ColorMap[],2,false) & ")" -> 124 - Delicate Luminous Scene (Yellow) | F35: =IFERROR(__xludf.DUMMYFUNCTION("""COMPUTED_VALUE"""),"7001401-Physical Attack Up +1") -> 7001401-Physical Attack Up +1 | G35: =IFERROR(__xludf.DUMMYFUNCTION("""COMPUTED_VALUE"""),"7001501-Magic Attack Power Up +1") -> 7001501-Magic Attack Power Up +1 | H35: =IFERROR(__xludf.DUMMYFUNCTION("""COMPUTED_VALUE"""),"7001601-Fire Attack Power Up +1") -> 7001601-Fire Attack Power Up +1 | M35: 7001400 | N35: 7001500 | O35: 7001600
A36: 125 | B36: Polished Luminous Scene | C36: 2 | D36: =A36 & " - " & B36 & " (" & VLOOKUP(C36, Tbl_ColorMap[],2,false) & ")" -> 125 - Polished Luminous Scene (Yellow) | F36: =IFERROR(__xludf.DUMMYFUNCTION("""COMPUTED_VALUE"""),"7001402-Physical Attack Up +2") -> 7001402-Physical Attack Up +2 | G36: =IFERROR(__xludf.DUMMYFUNCTION("""COMPUTED_VALUE"""),"7001502-Magic Attack Power Up +2") -> 7001502-Magic Attack Power Up +2 | H36: =IFERROR(__xludf.DUMMYFUNCTION("""COMPUTED_VALUE"""),"7001602-Fire Attack Power Up +2") -> 7001602-Fire Attack Power Up +2 | M36: 7001401 | N36: 7001501 | O36: 7001601
A37: 126 | B37: Grand Luminous Scene | C37: 2 | D37: =A37 & " - " & B37 & " (" & VLOOKUP(C37, Tbl_ColorMap[],2,false) & ")" -> 126 - Grand Luminous Scene (Yellow) | F37: =IFERROR(__xludf.DUMMYFUNCTION("""COMPUTED_VALUE"""),"7001500-Magic Attack Power Up") -> 7001500-Magic Attack Power Up | G37: =IFERROR(__xludf.DUMMYFUNCTION("""COMPUTED_VALUE"""),"7001600-Fire Attack Power Up") -> 7001600-Fire Attack Power Up | H37: =IFERROR(__xludf.DUMMYFUNCTION("""COMPUTED_VALUE"""),"7001700-Lightning Attack Power Up") -> 7001700-Lightning Attack Power Up | M37: 7001402 | N37: 7001502 | O37: 7001602
A38: 127 | B38: Delicate Tranquil Scene | C38: 3 | D38: =A38 & " - " & B38 & " (" & VLOOKUP(C38, Tbl_ColorMap[],2,false) & ")" -> 127 - Delicate Tranquil Scene (Green) | F38: =IFERROR(__xludf.DUMMYFUNCTION("""COMPUTED_VALUE"""),"7001501-Magic Attack Power Up +1") -> 7001501-Magic Attack Power Up +1 | G38: =IFERROR(__xludf.DUMMYFUNCTION("""COMPUTED_VALUE"""),"7001601-Fire Attack Power Up +1") -> 7001601-Fire Attack Power Up +1 | H38: =IFERROR(__xludf.DUMMYFUNCTION("""COMPUTED_VALUE"""),"7001701-Lightning Attack Power Up +1") -> 7001701-Lightning Attack Power Up +1 | M38: 7001500 | N38: 7001600 | O38: 7001700
A39: 128 | B39: Polished Tranquil Scene | C39: 3 | D39: =A39 & " - " & B39 & " (" & VLOOKUP(C39, Tbl_ColorMap[],2,false) & ")" -> 128 - Polished Tranquil Scene (Green) | F39: =IFERROR(__xludf.DUMMYFUNCTION("""COMPUTED_VALUE"""),"7001502-Magic Attack Power Up +2") -> 7001502-Magic Attack Power Up +2 | G39: =IFERROR(__xludf.DUMMYFUNCTION("""COMPUTED_VALUE"""),"7001602-Fire Attack Power Up +2") -> 7001602-Fire Attack Power Up +2 | H39: =IFERROR(__xludf.DUMMYFUNCTION("""COMPUTED_VALUE"""),"7001702-Lightning Attack Power Up +2") -> 7001702-Lightning Attack Power Up +2 | M39: 7001501 | N39: 7001601 | O39: 7001701
A40: 129 | B40: Grand Tranquil Scene | C40: 3 | D40: =A40 & " - " & B40 & " (" & VLOOKUP(C40, Tbl_ColorMap[],2,false) & ")" -> 129 - Grand Tranquil Scene (Green) | F40: =IFERROR(__xludf.DUMMYFUNCTION("""COMPUTED_VALUE"""),"7001600-Fire Attack Power Up") -> 7001600-Fire Attack Power Up | G40: =IFERROR(__xludf.DUMMYFUNCTION("""COMPUTED_VALUE"""),"7001700-Lightning Attack Power Up") -> 7001700-Lightning Attack Power Up | H40: =IFERROR(__xludf.DUMMYFUNCTION("""COMPUTED_VALUE"""),"7001800-Holy Attack Power Up") -> 7001800-Holy Attack Power Up | M40: 7001502 | N40: 7001602 | O40: 7001702
A41: 130 | B41: Delicate Tranquil Scene | C41: 3 | D41: =A41 & " - " & B41 & " (" & VLOOKUP(C41, Tbl_ColorMap[],2,false) & ")" -> 130 - Delicate Tranquil Scene (Green) | F41: =IFERROR(__xludf.DUMMYFUNCTION("""COMPUTED_VALUE"""),"7001601-Fire Attack Power Up +1") -> 7001601-Fire Attack Power Up +1 | G41: =IFERROR(__xludf.DUMMYFUNCTION("""COMPUTED_VALUE"""),"7001701-Lightning Attack Power Up +1") -> 7001701-Lightning Attack Power Up +1 | H41: =IFERROR(__xludf.DUMMYFUNCTION("""COMPUTED_VALUE"""),"7001801-Holy Attack Power Up +1") -> 7001801-Holy Attack Power Up +1 | M41: 7001600 | N41: 7001700 | O41: 7001800
A42: 131 | B42: Polished Tranquil Scene | C42: 3 | D42: =A42 & " - " & B42 & " (" & VLOOKUP(C42, Tbl_ColorMap[],2,false) & ")" -> 131 - Polished Tranquil Scene (Green) | F42: =IFERROR(__xludf.DUMMYFUNCTION("""COMPUTED_VALUE"""),"7001602-Fire Attack Power Up +2") -> 7001602-Fire Attack Power Up +2 | G42: =IFERROR(__xludf.DUMMYFUNCTION("""COMPUTED_VALUE"""),"7001702-Lightning Attack Power Up +2") -> 7001702-Lightning Attack Power Up +2 | H42: =IFERROR(__xludf.DUMMYFUNCTION("""COMPUTED_VALUE"""),"7001802-Holy Attack Power Up +2") -> 7001802-Holy Attack Power Up +2 | M42: 7001601 | N42: 7001701 | O42: 7001801
A43: 132 | B43: Grand Tranquil Scene | C43: 3 | D43: =A43 & " - " & B43 & " (" & VLOOKUP(C43, Tbl_ColorMap[],2,false) & ")" -> 132 - Grand Tranquil Scene (Green) | F43: =IFERROR(__xludf.DUMMYFUNCTION("""COMPUTED_VALUE"""),"7001700-Lightning Attack Power Up") -> 7001700-Lightning Attack Power Up | G43: =IFERROR(__xludf.DUMMYFUNCTION("""COMPUTED_VALUE"""),"7001800-Holy Attack Power Up") -> 7001800-Holy Attack Power Up | H43: =IFERROR(__xludf.DUMMYFUNCTION("""COMPUTED_VALUE"""),"7002600-Magic Damage Negation Up") -> 7002600-Magic Damage Negation Up | M43: 7001602 | N43: 7001702 | O43: 7001802
A44: 133 | B44: Delicate Tranquil Scene | C44: 3 | D44: =A44 & " - " & B44 & " (" & VLOOKUP(C44, Tbl_ColorMap[],2,false) & ")" -> 133 - Delicate Tranquil Scene (Green) | F44: =IFERROR(__xludf.DUMMYFUNCTION("""COMPUTED_VALUE"""),"7001701-Lightning Attack Power Up +1") -> 7001701-Lightning Attack Power Up +1 | G44: =IFERROR(__xludf.DUMMYFUNCTION("""COMPUTED_VALUE"""),"7001801-Holy Attack Power Up +1") -> 7001801-Holy Attack Power Up +1 | H44: =IFERROR(__xludf.DUMMYFUNCTION("""COMPUTED_VALUE"""),"7002700-Fire Damage Negation Up") -> 7002700-Fire Damage Negation Up | M44: 7001700 | N44: 7001800 | O44: 7002600
A45: 134 | B45: Polished Tranquil Scene | C45: 3 | D45: =A45 & " - " & B45 & " (" & VLOOKUP(C45, Tbl_ColorMap[],2,false) & ")" -> 134 - Polished Tranquil Scene (Green) | F45: =IFERROR(__xludf.DUMMYFUNCTION("""COMPUTED_VALUE"""),"7001702-Lightning Attack Power Up +2") -> 7001702-Lightning Attack Power Up +2 | G45: =IFERROR(__xludf.DUMMYFUNCTION("""COMPUTED_VALUE"""),"7001802-Holy Attack Power Up +2") -> 7001802-Holy Attack Power Up +2 | H45: =IFERROR(__xludf.DUMMYFUNCTION("""COMPUTED_VALUE"""),"7002800-Lightning Damage Negation Up") -> 7002800-Lightning Damage Negation Up | M45: 7001701 | N45: 7001801 | O45: 7002700
A46: 135 | B46: Grand Tranquil Scene | C46: 3 | D46: =A46 & " - " & B46 & " (" & VLOOKUP(C46, Tbl_ColorMap[],2,false) & ")" -> 135 - Grand Tranquil Scene (Green) | F46: =IFERROR(__xludf.DUMMYFUNCTION("""COMPUTED_VALUE"""),"7001800-Holy Attack Power Up") -> 7001800-Holy Attack Power Up | G46: =IFERROR(__xludf.DUMMYFUNCTION("""COMPUTED_VALUE"""),"7002600-Magic Damage Negation Up") -> 7002600-Magic Damage Negation Up | H46: =IFERROR(__xludf.DUMMYFUNCTION("""COMPUTED_VALUE"""),"7002900-Holy Damage Negation Up") -> 7002900-Holy Damage Negation Up | M46: 7001702 | N46: 7001802 | O46: 7002800
A47: 200 | B47: Delicate Burning Scene | C47: 0 | D47: =A47 & " - " & B47 & " (" & VLOOKUP(C47, Tbl_ColorMap[],2,false) & ")" -> 200 - Delicate Burning Scene (Red) | F47: =IFERROR(__xludf.DUMMYFUNCTION("""COMPUTED_VALUE"""),"7001801-Holy Attack Power Up +1") -> 7001801-Holy Attack Power Up +1 | G47: =IFERROR(__xludf.DUMMYFUNCTION("""COMPUTED_VALUE"""),"7002700-Fire Damage Negation Up") -> 7002700-Fire Damage Negation Up | H47: =IFERROR(__xludf.DUMMYFUNCTION("""COMPUTED_VALUE"""),"7003000-Improved Poison Resistance") -> 7003000-Improved Poison Resistance | M47: 7001800 | N47: 7002600 | O47: 7002900
A48: 201 | B48: Polished Burning Scene | C48: 0 | D48: =A48 & " - " & B48 & " (" & VLOOKUP(C48, Tbl_ColorMap[],2,false) & ")" -> 201 - Polished Burning Scene (Red) | F48: =IFERROR(__xludf.DUMMYFUNCTION("""COMPUTED_VALUE"""),"7001802-Holy Attack Power Up +2") -> 7001802-Holy Attack Power Up +2 | G48: =IFERROR(__xludf.DUMMYFUNCTION("""COMPUTED_VALUE"""),"7002800-Lightning Damage Negation Up") -> 7002800-Lightning Damage Negation Up | H48: =IFERROR(__xludf.DUMMYFUNCTION("""COMPUTED_VALUE"""),"7003100-Improved Blood Loss Resistance") -> 7003100-Improved Blood Loss Resistance | M48: 7001801 | N48: 7002700 | O48: 7003000
A49: 202 | B49: Grand Burning Scene | C49: 0 | D49: =A49 & " - " & B49 & " (" & VLOOKUP(C49, Tbl_ColorMap[],2,false) & ")" -> 202 - Grand Burning Scene (Red) | F49: =IFERROR(__xludf.DUMMYFUNCTION("""COMPUTED_VALUE"""),"7002600-Magic Damage Negation Up") -> 7002600-Magic Damage Negation Up | G49: =IFERROR(__xludf.DUMMYFUNCTION("""COMPUTED_VALUE"""),"7002900-Holy Damage Negation Up") -> 7002900-Holy Damage Negation Up | H49: =IFERROR(__xludf.DUMMYFUNCTION("""COMPUTED_VALUE"""),"7003200-Improved Sleep Resistance") -> 7003200-Improved Sleep Resistance | M49: 7001802 | N49: 7002800 | O49: 7003100
A50: 203 | B50: Delicate Burning Scene | C50: 0 | D50: =A50 & " - " & B50 & " (" & VLOOKUP(C50, Tbl_ColorMap[],2,false) & ")" -> 203 - Delicate Burning Scene (Red) | F50: =IFERROR(__xludf.DUMMYFUNCTION("""COMPUTED_VALUE"""),"7002700-Fire Damage Negation Up") -> 7002700-Fire Damage Negation Up | G50: =IFERROR(__xludf.DUMMYFUNCTION("""COMPUTED_VALUE"""),"7003000-Improved Poison Resistance") -> 7003000-Improved Poison Resistance | H50: =IFERROR(__xludf.DUMMYFUNCTION("""COMPUTED_VALUE"""),"7003300-Improved Death Blight Resistance") -> 7003300-Improved Death Blight Resistance | M50: 7002600 | N50: 7002900 | O50: 7003200
A51: 204 | B51: Polished Burning Scene | C51: 0 | D51: =A51 & " - " & B51 & " (" & VLOOKUP(C51, Tbl_ColorMap[],2,false) & ")" -> 204 - Polished Burning Scene (Red) | F51: =IFERROR(__xludf.DUMMYFUNCTION("""COMPUTED_VALUE"""),"7002800-Lightning Damage Negation Up") -> 7002800-Lightning Damage Negation Up | G51: =IFERROR(__xludf.DUMMYFUNCTION("""COMPUTED_VALUE"""),"7003100-Improved Blood Loss Resistance") -> 7003100-Improved Blood Loss Resistance | H51: =IFERROR(__xludf.DUMMYFUNCTION("""COMPUTED_VALUE"""),"7003400-Improved Rot Resistance") -> 7003400-Improved Rot Resistance | M51: 7002700 | N51: 7003000 | O51: 7003300
A52: 205 | B52: Grand Burning Scene | C52: 0 | D52: =A52 & " - " & B52 & " (" & VLOOKUP(C52, Tbl_ColorMap[],2,false) & ")" -> 205 - Grand Burning Scene (Red) | F52: =IFERROR(__xludf.DUMMYFUNCTION("""COMPUTED_VALUE"""),"7002900-Holy Damage Negation Up") -> 7002900-Holy Damage Negation Up | G52: =IFERROR(__xludf.DUMMYFUNCTION("""COMPUTED_VALUE"""),"7003200-Improved Sleep Resistance") -> 7003200-Improved Sleep Resistance | H52: =IFERROR(__xludf.DUMMYFUNCTION("""COMPUTED_VALUE"""),"7003500-Improved Frost Resistance") -> 7003500-Improved Frost Resistance | M52: 7002800 | N52: 7003100 | O52: 7003400
A53: 206 | B53: Delicate Burning Scene | C53: 0 | D53: =A53 & " - " & B53 & " (" & VLOOKUP(C53, Tbl_ColorMap[],2,false) & ")" -> 206 - Delicate Burning Scene (Red) | F53: =IFERROR(__xludf.DUMMYFUNCTION("""COMPUTED_VALUE"""),"7003000-Improved Poison Resistance") -> 7003000-Improved Poison Resistance | G53: =IFERROR(__xludf.DUMMYFUNCTION("""COMPUTED_VALUE"""),"7003300-Improved Death Blight Resistance") -> 7003300-Improved Death Blight Resistance | H53: =IFERROR(__xludf.DUMMYFUNCTION("""COMPUTED_VALUE"""),"7003600-Improved Madness Resistance") -> 7003600-Improved Madness Resistance | M53: 7002900 | N53: 7003200 | O53: 7003500
A54: 207 | B54: Polished Burning Scene | C54: 0 | D54: =A54 & " - " & B54 & " (" & VLOOKUP(C54, Tbl_ColorMap[],2,false) & ")" -> 207 - Polished Burning Scene (Red) | F54: =IFERROR(__xludf.DUMMYFUNCTION("""COMPUTED_VALUE"""),"7003100-Improved Blood Loss Resistance") -> 7003100-Improved Blood Loss Resistance | G54: =IFERROR(__xludf.DUMMYFUNCTION("""COMPUTED_VALUE"""),"7003400-Improved Rot Resistance") -> 7003400-Improved Rot Resistance | H54: =IFERROR(__xludf.DUMMYFUNCTION("""COMPUTED_VALUE"""),"7005600-Partial HP Restoration upon Post-Damage Attacks") -> 7005600-Partial HP Restoration upon Post-Damage Attacks | M54: 7003000 | N54: 7003300 | O54: 7003600
A55: 208 | B55: Grand Burning Scene | C55: 0 | D55: =A55 & " - " & B55 & " (" & VLOOKUP(C55, Tbl_ColorMap[],2,false) & ")" -> 208 - Grand Burning Scene (Red) | F55: =IFERROR(__xludf.DUMMYFUNCTION("""COMPUTED_VALUE"""),"7003200-Improved Sleep Resistance") -> 7003200-Improved Sleep Resistance | G55: =IFERROR(__xludf.DUMMYFUNCTION("""COMPUTED_VALUE"""),"7003500-Improved Frost Resistance") -> 7003500-Improved Frost Resistance | H55: =IFERROR(__xludf.DUMMYFUNCTION("""COMPUTED_VALUE"""),"7006000-Improved Stance-Breaking when Two-Handing") -> 7006000-Improved Stance-Breaking when Two-Handing | M55: 7003100 | N55: 7003400 | O55: 7005600
A56: 209 | B56: Delicate Drizzly Scene | C56: 1 | D56: =A56 & " - " & B56 & " (" & VLOOKUP(C56, Tbl_ColorMap[],2,false) & ")" -> 209 - Delicate Drizzly Scene (Blue) | F56: =IFERROR(__xludf.DUMMYFUNCTION("""COMPUTED_VALUE"""),"7003300-Improved Death Blight Resistance") -> 7003300-Improved Death Blight Resistance | G56: =IFERROR(__xludf.DUMMYFUNCTION("""COMPUTED_VALUE"""),"7003600-Improved Madness Resistance") -> 7003600-Improved Madness Resistance | H56: =IFERROR(__xludf.DUMMYFUNCTION("""COMPUTED_VALUE"""),"7006100-Improved Stance-Breaking when Wielding Two Armaments") -> 7006100-Improved Stance-Breaking when Wielding Two Armaments | M56: 7003200 | N56: 7003500 | O56: 7006000
A57: 210 | B57: Polished Drizzly Scene | C57: 1 | D57: =A57 & " - " & B57 & " (" & VLOOKUP(C57, Tbl_ColorMap[],2,false) & ")" -> 210 - Polished Drizzly Scene (Blue) | F57: =IFERROR(__xludf.DUMMYFUNCTION("""COMPUTED_VALUE"""),"7003400-Improved Rot Resistance") -> 7003400-Improved Rot Resistance | G57: =IFERROR(__xludf.DUMMYFUNCTION("""COMPUTED_VALUE"""),"7005600-Partial HP Restoration upon Post-Damage Attacks") -> 7005600-Partial HP Restoration upon Post-Damage Attacks | H57: =IFERROR(__xludf.DUMMYFUNCTION("""COMPUTED_VALUE"""),"7010200-Flask Also Heals Allies") -> 7010200-Flask Also Heals Allies | M57: 7003300 | N57: 7003600 | O57: 7006100
A58: 211 | B58: Grand Drizzly Scene | C58: 1 | D58: =A58 & " - " & B58 & " (" & VLOOKUP(C58, Tbl_ColorMap[],2,false) & ")" -> 211 - Grand Drizzly Scene (Blue) | F58: =IFERROR(__xludf.DUMMYFUNCTION("""COMPUTED_VALUE"""),"7003500-Improved Frost Resistance") -> 7003500-Improved Frost Resistance | G58: =IFERROR(__xludf.DUMMYFUNCTION("""COMPUTED_VALUE"""),"7006000-Improved Stance-Breaking when Two-Handing") -> 7006000-Improved Stance-Breaking when Two-Handing | H58: =IFERROR(__xludf.DUMMYFUNCTION("""COMPUTED_VALUE"""),"7010500-[Wylder] Art activation spreads fire in area") -> 7010500-[Wylder] Art activation spreads fire in area | M58: 7003400 | N58: 7005600 | O58: 7010200
A59: 212 | B59: Delicate Drizzly Scene | C59: 1 | D59: =A59 & " - " & B59 & " (" & VLOOKUP(C59, Tbl_ColorMap[],2,false) & ")" -> 212 - Delicate Drizzly Scene (Blue) | F59: =IFERROR(__xludf.DUMMYFUNCTION("""COMPUTED_VALUE"""),"7003600-Improved Madness Resistance") -> 7003600-Improved Madness Resistance | G59: =IFERROR(__xludf.DUMMYFUNCTION("""COMPUTED_VALUE"""),"7006100-Improved Stance-Breaking when Wielding Two Armaments") -> 7006100-Improved Stance-Breaking when Wielding Two Armaments | H59: =IFERROR(__xludf.DUMMYFUNCTION("""COMPUTED_VALUE"""),"7010700-[Duchess] Successive dagger attack reprises event upon nearby enemies") -> 7010700-[Duchess] Successive dagger attack reprises event upon nearby enemies | M59: 7003500 | N59: 7006000 | O59: 7010500
A60: 213 | B60: Polished Drizzly Scene | C60: 1 | D60: =A60 & " - " & B60 & " (" & VLOOKUP(C60, Tbl_ColorMap[],2,false) & ")" -> 213 - Polished Drizzly Scene (Blue) | F60: =IFERROR(__xludf.DUMMYFUNCTION("""COMPUTED_VALUE"""),"7005600-Partial HP Restoration upon Post-Damage Attacks") -> 7005600-Partial HP Restoration upon Post-Damage Attacks | G60: =IFERROR(__xludf.DUMMYFUNCTION("""COMPUTED_VALUE"""),"7010200-Flask Also Heals Allies") -> 7010200-Flask Also Heals Allies | H60: =IFERROR(__xludf.DUMMYFUNCTION("""COMPUTED_VALUE"""),"7010900-[Revenant] Expend own HP to fully heal nearby allies when activating Art") -> 7010900-[Revenant] Expend own HP to fully heal nearby allies when activating Art | M60: 7003600 | N60: 7006100 | O60: 7010700
A61: 214 | B61: Grand Drizzly Scene | C61: 1 | D61: =A61 & " - " & B61 & " (" & VLOOKUP(C61, Tbl_ColorMap[],2,false) & ")" -> 214 - Grand Drizzly Scene (Blue) | F61: =IFERROR(__xludf.DUMMYFUNCTION("""COMPUTED_VALUE"""),"7006000-Improved Stance-Breaking when Two-Handing") -> 7006000-Improved Stance-Breaking when Two-Handing | G61: =IFERROR(__xludf.DUMMYFUNCTION("""COMPUTED_VALUE"""),"7010500-[Wylder] Art activation spreads fire in area") -> 7010500-[Wylder] Art activation spreads fire in area | H61: =IFERROR(__xludf.DUMMYFUNCTION("""COMPUTED_VALUE"""),"7011000-[Guardian] Increased duration for Character Skill") -> 7011000-[Guardian] Increased duration for Character Skill | M61: 7005600 | N61: 7010200 | O61: 7010900
A62: 215 | B62: Delicate Drizzly Scene | C62: 1 | D62: =A62 & " - " & B62 & " (" & VLOOKUP(C62, Tbl_ColorMap[],2,false) & ")" -> 215 - Delicate Drizzly Scene (Blue) | F62: =IFERROR(__xludf.DUMMYFUNCTION("""COMPUTED_VALUE"""),"7006100-Improved Stance-Breaking when Wielding Two Armaments") -> 7006100-Improved Stance-Breaking when Wielding Two Armaments | G62: =IFERROR(__xludf.DUMMYFUNCTION("""COMPUTED_VALUE"""),"7010700-[Duchess] Successive dagger attack reprises event upon nearby enemies") -> 7010700-[Duchess] Successive dagger attack reprises event upon nearby enemies | H62: =IFERROR(__xludf.DUMMYFUNCTION("""COMPUTED_VALUE"""),"7011200-[Revenant] Trigger ghostflame explosion during Ultimate Art activation") -> 7011200-[Revenant] Trigger ghostflame explosion during Ultimate Art activation | M62: 7006000 | N62: 7010500 | O62: 7011000
A63: 216 | B63: Polished Drizzly Scene | C63: 1 | D63: =A63 & " - " & B63 & " (" & VLOOKUP(C63, Tbl_ColorMap[],2,false) & ")" -> 216 - Polished Drizzly Scene (Blue) | F63: =IFERROR(__xludf.DUMMYFUNCTION("""COMPUTED_VALUE"""),"7010200-Flask Also Heals Allies") -> 7010200-Flask Also Heals Allies | G63: =IFERROR(__xludf.DUMMYFUNCTION("""COMPUTED_VALUE"""),"7010900-[Revenant] Expend own HP to fully heal nearby allies when activating Art") -> 7010900-[Revenant] Expend own HP to fully heal nearby allies when activating Art | H63: =IFERROR(__xludf.DUMMYFUNCTION("""COMPUTED_VALUE"""),"7011600-[Guardian] Creates whirlwind when charging halberd attacks") -> 7011600-[Guardian] Creates whirlwind when charging halberd attacks | M63: 7006100 | N63: 7010700 | O63: 7011200
A64: 217 | B64: Grand Drizzly Scene | C64: 1 | D64: =A64 & " - " & B64 & " (" & VLOOKUP(C64, Tbl_ColorMap[],2,false) & ")" -> 217 - Grand Drizzly Scene (Blue) | F64: =IFERROR(__xludf.DUMMYFUNCTION("""COMPUTED_VALUE"""),"7010500-[Wylder] Art activation spreads fire in area") -> 7010500-[Wylder] Art activation spreads fire in area | G64: =IFERROR(__xludf.DUMMYFUNCTION("""COMPUTED_VALUE"""),"7011000-[Guardian] Increased duration for Character Skill") -> 7011000-[Guardian] Increased duration for Character Skill | H64: =IFERROR(__xludf.DUMMYFUNCTION("""COMPUTED_VALUE"""),"7011700-[Executor] Roaring restores HP while Art is active") -> 7011700-[Executor] Roaring restores HP while Art is active | M64: 7010200 | N64: 7010900 | O64: 7011600
A65: 218 | B65: Delicate Luminous Scene | C65: 2 | D65: =A65 & " - " & B65 & " (" & VLOOKUP(C65, Tbl_ColorMap[],2,false) & ")" -> 218 - Delicate Luminous Scene (Yellow) | F65: =IFERROR(__xludf.DUMMYFUNCTION("""COMPUTED_VALUE"""),"7010700-[Duchess] Successive dagger attack reprises event upon nearby enemies") -> 7010700-[Duchess] Successive dagger attack reprises event upon nearby enemies | G65: =IFERROR(__xludf.DUMMYFUNCTION("""COMPUTED_VALUE"""),"7011200-[Revenant] Trigger ghostflame explosion during Ultimate Art activation") -> 7011200-[Revenant] Trigger ghostflame explosion during Ultimate Art activation | H65: =IFERROR(__xludf.DUMMYFUNCTION("""COMPUTED_VALUE"""),"7012000-[Guardian] Slowly restores nearby allies' HP while Art is active") -> 7012000-[Guardian] Slowly restores nearby allies' HP while Art is active | M65: 7010500 | N65: 7011000 | O65: 7011700
A66: 219 | B66: Polished Luminous Scene | C66: 2 | D66: =A66 & " - " & B66 & " (" & VLOOKUP(C66, Tbl_ColorMap[],2,false) & ")" -> 219 - Polished Luminous Scene (Yellow) | F66: =IFERROR(__xludf.DUMMYFUNCTION("""COMPUTED_VALUE"""),"7010900-[Revenant] Expend own HP to fully heal nearby allies when activating Art") -> 7010900-[Revenant] Expend own HP to fully heal nearby allies when activating Art | G66: =IFERROR(__xludf.DUMMYFUNCTION("""COMPUTED_VALUE"""),"7011600-[Guardian] Creates whirlwind when charging halberd attacks") -> 7011600-[Guardian] Creates whirlwind when charging halberd attacks | H66: =IFERROR(__xludf.DUMMYFUNCTION("""COMPUTED_VALUE"""),"7012200-Slowly restore HP for self and nearby allies when HP is low") -> 7012200-Slowly restore HP for self and nearby allies when HP is low | M66: 7010700 | N66: 7011200 | O66: 7012000
A67: 220 | B67: Grand Luminous Scene | C67: 2 | D67: =A67 & " - " & B67 & " (" & VLOOKUP(C67, Tbl_ColorMap[],2,false) & ")" -> 220 - Grand Luminous Scene (Yellow) | F67: =IFERROR(__xludf.DUMMYFUNCTION("""COMPUTED_VALUE"""),"7011000-[Guardian] Increased duration for Character Skill") -> 7011000-[Guardian] Increased duration for Character Skill | G67: =IFERROR(__xludf.DUMMYFUNCTION("""COMPUTED_VALUE"""),"7011700-[Executor] Roaring restores HP while Art is active") -> 7011700-[Executor] Roaring restores HP while Art is active | H67: =IFERROR(__xludf.DUMMYFUNCTION("""COMPUTED_VALUE"""),"7012300-Improved Damage Negation at Low HP") -> 7012300-Improved Damage Negation at Low HP | M67: 7010900 | N67: 7011600 | O67: 7012200
A68: 221 | B68: Delicate Luminous Scene | C68: 2 | D68: =A68 & " - " & B68 & " (" & VLOOKUP(C68, Tbl_ColorMap[],2,false) & ")" -> 221 - Delicate Luminous Scene (Yellow) | F68: =IFERROR(__xludf.DUMMYFUNCTION("""COMPUTED_VALUE"""),"7011200-[Revenant] Trigger ghostflame explosion during Ultimate Art activation") -> 7011200-[Revenant] Trigger ghostflame explosion during Ultimate Art activation | G68: =IFERROR(__xludf.DUMMYFUNCTION("""COMPUTED_VALUE"""),"7012000-[Guardian] Slowly restores nearby allies' HP while Art is active") -> 7012000-[Guardian] Slowly restores nearby allies' HP while Art is active | H68: =IFERROR(__xludf.DUMMYFUNCTION("""COMPUTED_VALUE"""),"7020000-[Wylder] Standard attacks enhanced with fiery follow-ups when using Character Skill (greatsword only)") -> 7020000-[Wylder] Standard attacks enhanced with fiery follow-ups when using Character Skill (greatsword only) | M68: 7011000 | N68: 7011700 | O68: 7012300
A69: 222 | B69: Polished Luminous Scene | C69: 2 | D69: =A69 & " - " & B69 & " (" & VLOOKUP(C69, Tbl_ColorMap[],2,false) & ")" -> 222 - Polished Luminous Scene (Yellow) | F69: =IFERROR(__xludf.DUMMYFUNCTION("""COMPUTED_VALUE"""),"7011600-[Guardian] Creates whirlwind when charging halberd attacks") -> 7011600-[Guardian] Creates whirlwind when charging halberd attacks | G69: =IFERROR(__xludf.DUMMYFUNCTION("""COMPUTED_VALUE"""),"7012200-Slowly restore HP for self and nearby allies when HP is low") -> 7012200-Slowly restore HP for self and nearby allies when HP is low | H69: =IFERROR(__xludf.DUMMYFUNCTION("""COMPUTED_VALUE"""),"7030000-Improved Poise Near Totem Stela") -> 7030000-Improved Poise Near Totem Stela | M69: 7011200 | N69: 7012000 | O69: 7020000
A70: 223 | B70: Grand Luminous Scene | C70: 2 | D70: =A70 & " - " & B70 & " (" & VLOOKUP(C70, Tbl_ColorMap[],2,false) & ")" -> 223 - Grand Luminous Scene (Yellow) | F70: =IFERROR(__xludf.DUMMYFUNCTION("""COMPUTED_VALUE"""),"7011700-[Executor] Roaring restores HP while Art is active") -> 7011700-[Executor] Roaring restores HP while Art is active | G70: =IFERROR(__xludf.DUMMYFUNCTION("""COMPUTED_VALUE"""),"7012300-Improved Damage Negation at Low HP") -> 7012300-Improved Damage Negation at Low HP | H70: =IFERROR(__xludf.DUMMYFUNCTION("""COMPUTED_VALUE"""),"7030200-HP restored when using medicinal boluses, etc.") -> 7030200-HP restored when using medicinal boluses, etc. | M70: 7011600 | N70: 7012200 | O70: 7030000
A71: 224 | B71: Delicate Luminous Scene | C71: 2 | D71: =A71 & " - " & B71 & " (" & VLOOKUP(C71, Tbl_ColorMap[],2,false) & ")" -> 224 - Delicate Luminous Scene (Yellow) | F71: =IFERROR(__xludf.DUMMYFUNCTION("""COMPUTED_VALUE"""),"7012000-[Guardian] Slowly restores nearby allies' HP while Art is active") -> 7012000-[Guardian] Slowly restores nearby allies' HP while Art is active | G71: =IFERROR(__xludf.DUMMYFUNCTION("""COMPUTED_VALUE"""),"7020000-[Wylder] Standard attacks enhanced with fiery follow-ups when using Character Skill (greatsword only)") -> 7020000-[Wylder] Standard attacks enhanced with fiery follow-ups when using Character Skill (greatsword only) | H71: =IFERROR(__xludf.DUMMYFUNCTION("""COMPUTED_VALUE"""),"7030600-Successful guarding fills more of the Art gauge") -> 7030600-Successful guarding fills more of the Art gauge | M71: 7011700 | N71: 7012300 | O71: 7030200
A72: 225 | B72: Polished Luminous Scene | C72: 2 | D72: =A72 & " - " & B72 & " (" & VLOOKUP(C72, Tbl_ColorMap[],2,false) & ")" -> 225 - Polished Luminous Scene (Yellow) | F72: =IFERROR(__xludf.DUMMYFUNCTION("""COMPUTED_VALUE"""),"7012200-Slowly restore HP for self and nearby allies when HP is low") -> 7012200-Slowly restore HP for self and nearby allies when HP is low | G72: =IFERROR(__xludf.DUMMYFUNCTION("""COMPUTED_VALUE"""),"7030000-Improved Poise Near Totem Stela") -> 7030000-Improved Poise Near Totem Stela | H72: =IFERROR(__xludf.DUMMYFUNCTION("""COMPUTED_VALUE"""),"7030700-Draw enemy attention while guarding") -> 7030700-Draw enemy attention while guarding | M72: 7012000 | N72: 7020000 | O72: 7030600
A73: 226 | B73: Grand Luminous Scene | C73: 2 | D73: =A73 & " - " & B73 & " (" & VLOOKUP(C73, Tbl_ColorMap[],2,false) & ")" -> 226 - Grand Luminous Scene (Yellow) | F73: =IFERROR(__xludf.DUMMYFUNCTION("""COMPUTED_VALUE"""),"7012300-Improved Damage Negation at Low HP") -> 7012300-Improved Damage Negation at Low HP | G73: =IFERROR(__xludf.DUMMYFUNCTION("""COMPUTED_VALUE"""),"7030200-HP restored when using medicinal boluses, etc.") -> 7030200-HP restored when using medicinal boluses, etc. | H73: =IFERROR(__xludf.DUMMYFUNCTION("""COMPUTED_VALUE"""),"7030800-Critical hits fill more of the Art gauge") -> 7030800-Critical hits fill more of the Art gauge | M73: 7012200 | N73: 7030000 | O73: 7030700
A74: 227 | B74: Delicate Tranquil Scene | C74: 3 | D74: =A74 & " - " & B74 & " (" & VLOOKUP(C74, Tbl_ColorMap[],2,false) & ")" -> 227 - Delicate Tranquil Scene (Green) | F74: =IFERROR(__xludf.DUMMYFUNCTION("""COMPUTED_VALUE"""),"7020000-[Wylder] Standard attacks enhanced with fiery follow-ups when using Character Skill (greatsword only)") -> 7020000-[Wylder] Standard attacks enhanced with fiery follow-ups when using Character Skill (greatsword only) | G74: =IFERROR(__xludf.DUMMYFUNCTION("""COMPUTED_VALUE"""),"7030600-Successful guarding fills more of the Art gauge") -> 7030600-Successful guarding fills more of the Art gauge | H74: =IFERROR(__xludf.DUMMYFUNCTION("""COMPUTED_VALUE"""),"7030900-Physical attack power increases after using grease items") -> 7030900-Physical attack power increases after using grease items | M74: 7012300 | N74: 7030200 | O74: 7030800
A75: 228 | B75: Polished Tranquil Scene | C75: 3 | D75: =A75 & " - " & B75 & " (" & VLOOKUP(C75, Tbl_ColorMap[],2,false) & ")" -> 228 - Polished Tranquil Scene (Green) | F75: =IFERROR(__xludf.DUMMYFUNCTION("""COMPUTED_VALUE"""),"7030000-Improved Poise Near Totem Stela") -> 7030000-Improved Poise Near Totem Stela | G75: =IFERROR(__xludf.DUMMYFUNCTION("""COMPUTED_VALUE"""),"7030700-Draw enemy attention while guarding") -> 7030700-Draw enemy attention while guarding | H75: =IFERROR(__xludf.DUMMYFUNCTION("""COMPUTED_VALUE"""),"7031200-[Revenant] Strengthens family and allies when Ultimate Art is activated") -> 7031200-[Revenant] Strengthens family and allies when Ultimate Art is activated | M75: 7020000 | N75: 7030600 | O75: 7030900
A76: 229 | B76: Grand Tranquil Scene | C76: 3 | D76: =A76 & " - " & B76 & " (" & VLOOKUP(C76, Tbl_ColorMap[],2,false) & ")" -> 229 - Grand Tranquil Scene (Green) | F76: =IFERROR(__xludf.DUMMYFUNCTION("""COMPUTED_VALUE"""),"7030200-HP restored when using medicinal boluses, etc.") -> 7030200-HP restored when using medicinal boluses, etc. | G76: =IFERROR(__xludf.DUMMYFUNCTION("""COMPUTED_VALUE"""),"7030800-Critical hits fill more of the Art gauge") -> 7030800-Critical hits fill more of the Art gauge | H76: =IFERROR(__xludf.DUMMYFUNCTION("""COMPUTED_VALUE"""),"7031300-[Raider] Damage taken while using Character Skill improves attack power and stamina") -> 7031300-[Raider] Damage taken while using Character Skill improves attack power and stamina | M76: 7030000 | N76: 7030700 | O76: 7031200
A77: 230 | B77: Delicate Tranquil Scene | C77: 3 | D77: =A77 & " - " & B77 & " (" & VLOOKUP(C77, Tbl_ColorMap[],2,false) & ")" -> 230 - Delicate Tranquil Scene (Green) | F77: =IFERROR(__xludf.DUMMYFUNCTION("""COMPUTED_VALUE"""),"7030600-Successful guarding fills more of the Art gauge") -> 7030600-Successful guarding fills more of the Art gauge | G77: =IFERROR(__xludf.DUMMYFUNCTION("""COMPUTED_VALUE"""),"7030900-Physical attack power increases after using grease items") -> 7030900-Physical attack power increases after using grease items | H77: =IFERROR(__xludf.DUMMYFUNCTION("""COMPUTED_VALUE"""),"7031800-[Duchess] Become difficult to spot and silence footsteps after landing critical from behind") -> 7031800-[Duchess] Become difficult to spot and silence footsteps after landing critical from behind | M77: 7030200 | N77: 7030800 | O77: 7031300
A78: 231 | B78: Polished Tranquil Scene | C78: 3 | D78: =A78 & " - " & B78 & " (" & VLOOKUP(C78, Tbl_ColorMap[],2,false) & ")" -> 231 - Polished Tranquil Scene (Green) | F78: =IFERROR(__xludf.DUMMYFUNCTION("""COMPUTED_VALUE"""),"7030700-Draw enemy attention while guarding") -> 7030700-Draw enemy attention while guarding | G78: =IFERROR(__xludf.DUMMYFUNCTION("""COMPUTED_VALUE"""),"7031200-[Revenant] Strengthens family and allies when Ultimate Art is activated") -> 7031200-[Revenant] Strengthens family and allies when Ultimate Art is activated | H78: =IFERROR(__xludf.DUMMYFUNCTION("""COMPUTED_VALUE"""),"7031900-Critical Hits Earn Runes") -> 7031900-Critical Hits Earn Runes | M78: 7030600 | N78: 7030900 | O78: 7031800
A79: 232 | B79: Grand Tranquil Scene | C79: 3 | D79: =A79 & " - " & B79 & " (" & VLOOKUP(C79, Tbl_ColorMap[],2,false) & ")" -> 232 - Grand Tranquil Scene (Green) | F79: =IFERROR(__xludf.DUMMYFUNCTION("""COMPUTED_VALUE"""),"7030800-Critical hits fill more of the Art gauge") -> 7030800-Critical hits fill more of the Art gauge | G79: =IFERROR(__xludf.DUMMYFUNCTION("""COMPUTED_VALUE"""),"7031300-[Raider] Damage taken while using Character Skill improves attack power and stamina") -> 7031300-[Raider] Damage taken while using Character Skill improves attack power and stamina | H79: =IFERROR(__xludf.DUMMYFUNCTION("""COMPUTED_VALUE"""),"7032200-Taking attacks improves attack power") -> 7032200-Taking attacks improves attack power | M79: 7030700 | N79: 7031200 | O79: 7031900
A80: 233 | B80: Delicate Tranquil Scene | C80: 3 | D80: =A80 & " - " & B80 & " (" & VLOOKUP(C80, Tbl_ColorMap[],2,false) & ")" -> 233 - Delicate Tranquil Scene (Green) | F80: =IFERROR(__xludf.DUMMYFUNCTION("""COMPUTED_VALUE"""),"7030900-Physical attack power increases after using grease items") -> 7030900-Physical attack power increases after using grease items | G80: =IFERROR(__xludf.DUMMYFUNCTION("""COMPUTED_VALUE"""),"7031800-[Duchess] Become difficult to spot and silence footsteps after landing critical from behind") -> 7031800-[Duchess] Become difficult to spot and silence footsteps after landing critical from behind | H80: =IFERROR(__xludf.DUMMYFUNCTION("""COMPUTED_VALUE"""),"7032400-[Wylder] Art gauge greatly filled when ability is activated") -> 7032400-[Wylder] Art gauge greatly filled when ability is activated | M80: 7030800 | N80: 7031300 | O80: 7032200
A81: 234 | B81: Polished Tranquil Scene | C81: 3 | D81: =A81 & " - " & B81 & " (" & VLOOKUP(C81, Tbl_ColorMap[],2,false) & ")" -> 234 - Polished Tranquil Scene (Green) | F81: =IFERROR(__xludf.DUMMYFUNCTION("""COMPUTED_VALUE"""),"7031200-[Revenant] Strengthens family and allies when Ultimate Art is activated") -> 7031200-[Revenant] Strengthens family and allies when Ultimate Art is activated | G81: =IFERROR(__xludf.DUMMYFUNCTION("""COMPUTED_VALUE"""),"7031900-Critical Hits Earn Runes") -> 7031900-Critical Hits Earn Runes | H81: =IFERROR(__xludf.DUMMYFUNCTION("""COMPUTED_VALUE"""),"7032700-[Duchess] Defeating enemies while Art is active ups attack power") -> 7032700-[Duchess] Defeating enemies while Art is active ups attack power | M81: 7030900 | N81: 7031800 | O81: 7032400
A82: 235 | B82: Grand Tranquil Scene | C82: 3 | D82: =A82 & " - " & B82 & " (" & VLOOKUP(C82, Tbl_ColorMap[],2,false) & ")" -> 235 - Grand Tranquil Scene (Green) | F82: =IFERROR(__xludf.DUMMYFUNCTION("""COMPUTED_VALUE"""),"7031300-[Raider] Damage taken while using Character Skill improves attack power and stamina") -> 7031300-[Raider] Damage taken while using Character Skill improves attack power and stamina | G82: =IFERROR(__xludf.DUMMYFUNCTION("""COMPUTED_VALUE"""),"7032200-Taking attacks improves attack power") -> 7032200-Taking attacks improves attack power | H82: =IFERROR(__xludf.DUMMYFUNCTION("""COMPUTED_VALUE"""),"7032800-[Recluse] Collecting affinity residue activates Terra Magica") -> 7032800-[Recluse] Collecting affinity residue activates Terra Magica | M82: 7031200 | N82: 7031900 | O82: 7032700
A83: 1000 | B83: Delicate Burning Scene | C83: 0 | D83: =A83 & " - " & B83 & " (" & VLOOKUP(C83, Tbl_ColorMap[],2,false) & ")" -> 1000 - Delicate Burning Scene (Red) | F83: =IFERROR(__xludf.DUMMYFUNCTION("""COMPUTED_VALUE"""),"7031800-[Duchess] Become difficult to spot and silence footsteps after landing critical from behind") -> 7031800-[Duchess] Become difficult to spot and silence footsteps after landing critical from behind | G83: =IFERROR(__xludf.DUMMYFUNCTION("""COMPUTED_VALUE"""),"7032400-[Wylder] Art gauge greatly filled when ability is activated") -> 7032400-[Wylder] Art gauge greatly filled when ability is activated | H83: =IFERROR(__xludf.DUMMYFUNCTION("""COMPUTED_VALUE"""),"7032900-[Recluse] Suffer blood loss and increase attack power upon Art activation") -> 7032900-[Recluse] Suffer blood loss and increase attack power upon Art activation | M83: 7031300 | N83: 7032200 | O83: 7032800
A84: 1010 | B84: Delicate Drizzly Scene | C84: 1 | D84: =A84 & " - " & B84 & " (" & VLOOKUP(C84, Tbl_ColorMap[],2,false) & ")" -> 1010 - Delicate Drizzly Scene (Blue) | F84: =IFERROR(__xludf.DUMMYFUNCTION("""COMPUTED_VALUE"""),"7031900-Critical Hits Earn Runes") -> 7031900-Critical Hits Earn Runes | G84: =IFERROR(__xludf.DUMMYFUNCTION("""COMPUTED_VALUE"""),"7032700-[Duchess] Defeating enemies while Art is active ups attack power") -> 7032700-[Duchess] Defeating enemies while Art is active ups attack power | H84: =IFERROR(__xludf.DUMMYFUNCTION("""COMPUTED_VALUE"""),"7033200-[Wylder] +1 additional Character Skill use") -> 7033200-[Wylder] +1 additional Character Skill use | M84: 7031800 | N84: 7032400 | O84: 7032900
A85: 1020 | B85: Delicate Luminous Scene | C85: 2 | D85: =A85 & " - " & B85 & " (" & VLOOKUP(C85, Tbl_ColorMap[],2,false) & ")" -> 1020 - Delicate Luminous Scene (Yellow) | F85: =IFERROR(__xludf.DUMMYFUNCTION("""COMPUTED_VALUE"""),"7032200-Taking attacks improves attack power") -> 7032200-Taking attacks improves attack power | G85: =IFERROR(__xludf.DUMMYFUNCTION("""COMPUTED_VALUE"""),"7032800-[Recluse] Collecting affinity residue activates Terra Magica") -> 7032800-[Recluse] Collecting affinity residue activates Terra Magica | H85: =IFERROR(__xludf.DUMMYFUNCTION("""COMPUTED_VALUE"""),"7033400-[Guardian] Successful guards send out shockwaves while ability is active") -> 7033400-[Guardian] Successful guards send out shockwaves while ability is active | M85: 7031900 | N85: 7032700 | O85: 7033200
A86: 1030 | B86: Delicate Tranquil Scene | C86: 3 | D86: =A86 & " - " & B86 & " (" & VLOOKUP(C86, Tbl_ColorMap[],2,false) & ")" -> 1030 - Delicate Tranquil Scene (Green) | F86: =IFERROR(__xludf.DUMMYFUNCTION("""COMPUTED_VALUE"""),"7032400-[Wylder] Art gauge greatly filled when ability is activated") -> 7032400-[Wylder] Art gauge greatly filled when ability is activated | G86: =IFERROR(__xludf.DUMMYFUNCTION("""COMPUTED_VALUE"""),"7032900-[Recluse] Suffer blood loss and increase attack power upon Art activation") -> 7032900-[Recluse] Suffer blood loss and increase attack power upon Art activation | H86: =IFERROR(__xludf.DUMMYFUNCTION("""COMPUTED_VALUE"""),"7034100-[Recluse] Activating Ultimate Art raises Max HP") -> 7034100-[Recluse] Activating Ultimate Art raises Max HP | M86: 7032200 | N86: 7032800 | O86: 7033400
A87: 1040 | B87: Polished Burning Scene | C87: 0 | D87: =A87 & " - " & B87 & " (" & VLOOKUP(C87, Tbl_ColorMap[],2,false) & ")" -> 1040 - Polished Burning Scene (Red) | F87: =IFERROR(__xludf.DUMMYFUNCTION("""COMPUTED_VALUE"""),"7032700-[Duchess] Defeating enemies while Art is active ups attack power") -> 7032700-[Duchess] Defeating enemies while Art is active ups attack power | G87: =IFERROR(__xludf.DUMMYFUNCTION("""COMPUTED_VALUE"""),"7033200-[Wylder] +1 additional Character Skill use") -> 7033200-[Wylder] +1 additional Character Skill use | H87: =IFERROR(__xludf.DUMMYFUNCTION("""COMPUTED_VALUE"""),"7034400-[Executor] Character Skill Boosts Attack but Attacking Drains HP") -> 7034400-[Executor] Character Skill Boosts Attack but Attacking Drains HP | M87: 7032400 | N87: 7032900 | O87: 7034100
A88: 1050 | B88: Delicate Luminous Scene | C88: 2 | D88: =A88 & " - " & B88 & " (" & VLOOKUP(C88, Tbl_ColorMap[],2,false) & ")" -> 1050 - Delicate Luminous Scene (Yellow) | F88: =IFERROR(__xludf.DUMMYFUNCTION("""COMPUTED_VALUE"""),"7032800-[Recluse] Collecting affinity residue activates Terra Magica") -> 7032800-[Recluse] Collecting affinity residue activates Terra Magica | G88: =IFERROR(__xludf.DUMMYFUNCTION("""COMPUTED_VALUE"""),"7033400-[Guardian] Successful guards send out shockwaves while ability is active") -> 7033400-[Guardian] Successful guards send out shockwaves while ability is active | H88: =IFERROR(__xludf.DUMMYFUNCTION("""COMPUTED_VALUE"""),"7034500-[Executor] While Character Skill is active, unlocking use of cursed sword restores HP") -> 7034500-[Executor] While Character Skill is active, unlocking use of cursed sword restores HP | M88: 7032700 | N88: 7033200 | O88: 7034400
A89: 1060 | B89: Polished Tranquil Scene | C89: 3 | D89: =A89 & " - " & B89 & " (" & VLOOKUP(C89, Tbl_ColorMap[],2,false) & ")" -> 1060 - Polished Tranquil Scene (Green) | F89: =IFERROR(__xludf.DUMMYFUNCTION("""COMPUTED_VALUE"""),"7032900-[Recluse] Suffer blood loss and increase attack power upon Art activation") -> 7032900-[Recluse] Suffer blood loss and increase attack power upon Art activation | G89: =IFERROR(__xludf.DUMMYFUNCTION("""COMPUTED_VALUE"""),"7034100-[Recluse] Activating Ultimate Art raises Max HP") -> 7034100-[Recluse] Activating Ultimate Art raises Max HP | H89: =IFERROR(__xludf.DUMMYFUNCTION("""COMPUTED_VALUE"""),"7034600-[Ironeye] Art Charge Activation Adds Poison Effect") -> 7034600-[Ironeye] Art Charge Activation Adds Poison Effect | M89: 7032800 | N89: 7033400 | O89: 7034500
A90: 1070 | B90: Polished Drizzly Scene | C90: 1 | D90: =A90 & " - " & B90 & " (" & VLOOKUP(C90, Tbl_ColorMap[],2,false) & ")" -> 1070 - Polished Drizzly Scene (Blue) | F90: =IFERROR(__xludf.DUMMYFUNCTION("""COMPUTED_VALUE"""),"7033200-[Wylder] +1 additional Character Skill use") -> 7033200-[Wylder] +1 additional Character Skill use | G90: =IFERROR(__xludf.DUMMYFUNCTION("""COMPUTED_VALUE"""),"7034400-[Executor] Character Skill Boosts Attack but Attacking Drains HP") -> 7034400-[Executor] Character Skill Boosts Attack but Attacking Drains HP | H90: =IFERROR(__xludf.DUMMYFUNCTION("""COMPUTED_VALUE"""),"7034700-[Ironeye] Boosts thrusting counterattacks after executing Art") -> 7034700-[Ironeye] Boosts thrusting counterattacks after executing Art | M90: 7032900 | N90: 7034100 | O90: 7034600
A91: 1080 | B91: Polished Burning Scene | C91: 0 | D91: =A91 & " - " & B91 & " (" & VLOOKUP(C91, Tbl_ColorMap[],2,false) & ")" -> 1080 - Polished Burning Scene (Red) | F91: =IFERROR(__xludf.DUMMYFUNCTION("""COMPUTED_VALUE"""),"7033400-[Guardian] Successful guards send out shockwaves while ability is active") -> 7033400-[Guardian] Successful guards send out shockwaves while ability is active | G91: =IFERROR(__xludf.DUMMYFUNCTION("""COMPUTED_VALUE"""),"7034500-[Executor] While Character Skill is active, unlocking use of cursed sword restores HP") -> 7034500-[Executor] While Character Skill is active, unlocking use of cursed sword restores HP | H91: =IFERROR(__xludf.DUMMYFUNCTION("""COMPUTED_VALUE"""),"7035100-Critical Hit Boosts Stamina Recovery Speed") -> 7035100-Critical Hit Boosts Stamina Recovery Speed | M91: 7033200 | N91: 7034400 | O91: 7034700
A92: 1090 | B92: Polished Tranquil Scene | C92: 3 | D92: =A92 & " - " & B92 & " (" & VLOOKUP(C92, Tbl_ColorMap[],2,false) & ")" -> 1090 - Polished Tranquil Scene (Green) | F92: =IFERROR(__xludf.DUMMYFUNCTION("""COMPUTED_VALUE"""),"7034100-[Recluse] Activating Ultimate Art raises Max HP") -> 7034100-[Recluse] Activating Ultimate Art raises Max HP | G92: =IFERROR(__xludf.DUMMYFUNCTION("""COMPUTED_VALUE"""),"7034600-[Ironeye] Art Charge Activation Adds Poison Effect") -> 7034600-[Ironeye] Art Charge Activation Adds Poison Effect | H92: =IFERROR(__xludf.DUMMYFUNCTION("""COMPUTED_VALUE"""),"7036100-HP Recovery From Successful Guarding") -> 7036100-HP Recovery From Successful Guarding | M92: 7033400 | N92: 7034500 | O92: 7035100
A93: 1100 | B93: Polished Tranquil Scene | C93: 3 | D93: =A93 & " - " & B93 & " (" & VLOOKUP(C93, Tbl_ColorMap[],2,false) & ")" -> 1100 - Polished Tranquil Scene (Green) | F93: =IFERROR(__xludf.DUMMYFUNCTION("""COMPUTED_VALUE"""),"7034400-[Executor] Character Skill Boosts Attack but Attacking Drains HP") -> 7034400-[Executor] Character Skill Boosts Attack but Attacking Drains HP | G93: =IFERROR(__xludf.DUMMYFUNCTION("""COMPUTED_VALUE"""),"7034700-[Ironeye] Boosts thrusting counterattacks after executing Art") -> 7034700-[Ironeye] Boosts thrusting counterattacks after executing Art | H93: =IFERROR(__xludf.DUMMYFUNCTION("""COMPUTED_VALUE"""),"7040000-Improved Initial Standard Attack") -> 7040000-Improved Initial Standard Attack | M93: 7034100 | N93: 7034600 | O93: 7036100
A94: 1110 | B94: Polished Burning Scene | C94: 0 | D94: =A94 & " - " & B94 & " (" & VLOOKUP(C94, Tbl_ColorMap[],2,false) & ")" -> 1110 - Polished Burning Scene (Red) | F94: =IFERROR(__xludf.DUMMYFUNCTION("""COMPUTED_VALUE"""),"7034500-[Executor] While Character Skill is active, unlocking use of cursed sword restores HP") -> 7034500-[Executor] While Character Skill is active, unlocking use of cursed sword restores HP | G94: =IFERROR(__xludf.DUMMYFUNCTION("""COMPUTED_VALUE"""),"7035100-Critical Hit Boosts Stamina Recovery Speed") -> 7035100-Critical Hit Boosts Stamina Recovery Speed | H94: =IFERROR(__xludf.DUMMYFUNCTION("""COMPUTED_VALUE"""),"7040100-Improved Guard Counters") -> 7040100-Improved Guard Counters | M94: 7034400 | N94: 7034700 | O94: 7040000
A95: 1120 | B95: Polished Burning Scene | C95: 0 | D95: =A95 & " - " & B95 & " (" & VLOOKUP(C95, Tbl_ColorMap[],2,false) & ")" -> 1120 - Polished Burning Scene (Red) | F95: =IFERROR(__xludf.DUMMYFUNCTION("""COMPUTED_VALUE"""),"7034600-[Ironeye] Art Charge Activation Adds Poison Effect") -> 7034600-[Ironeye] Art Charge Activation Adds Poison Effect | G95: =IFERROR(__xludf.DUMMYFUNCTION("""COMPUTED_VALUE"""),"7036100-HP Recovery From Successful Guarding") -> 7036100-HP Recovery From Successful Guarding | H95: =IFERROR(__xludf.DUMMYFUNCTION("""COMPUTED_VALUE"""),"7040200-Improved Critical Hits") -> 7040200-Improved Critical Hits | M95: 7034500 | N95: 7035100 | O95: 7040100
A96: 1130 | B96: Polished Tranquil Scene | C96: 3 | D96: =A96 & " - " & B96 & " (" & VLOOKUP(C96, Tbl_ColorMap[],2,false) & ")" -> 1130 - Polished Tranquil Scene (Green) | F96: =IFERROR(__xludf.DUMMYFUNCTION("""COMPUTED_VALUE"""),"7034700-[Ironeye] Boosts thrusting counterattacks after executing Art") -> 7034700-[Ironeye] Boosts thrusting counterattacks after executing Art | G96: =IFERROR(__xludf.DUMMYFUNCTION("""COMPUTED_VALUE"""),"7040000-Improved Initial Standard Attack") -> 7040000-Improved Initial Standard Attack | H96: =IFERROR(__xludf.DUMMYFUNCTION("""COMPUTED_VALUE"""),"7040300-Improved Throwing Pot Damage") -> 7040300-Improved Throwing Pot Damage | M96: 7034600 | N96: 7036100 | O96: 7040200
A97: 1140 | B97: Polished Luminous Scene | C97: 2 | D97: =A97 & " - " & B97 & " (" & VLOOKUP(C97, Tbl_ColorMap[],2,false) & ")" -> 1140 - Polished Luminous Scene (Yellow) | F97: =IFERROR(__xludf.DUMMYFUNCTION("""COMPUTED_VALUE"""),"7035100-Critical Hit Boosts Stamina Recovery Speed") -> 7035100-Critical Hit Boosts Stamina Recovery Speed | G97: =IFERROR(__xludf.DUMMYFUNCTION("""COMPUTED_VALUE"""),"7040100-Improved Guard Counters") -> 7040100-Improved Guard Counters | H97: =IFERROR(__xludf.DUMMYFUNCTION("""COMPUTED_VALUE"""),"7040400-Improved Throwing Knife Damage") -> 7040400-Improved Throwing Knife Damage | M97: 7034700 | N97: 7040000 | O97: 7040300
A98: 1150 | B98: Polished Luminous Scene | C98: 2 | D98: =A98 & " - " & B98 & " (" & VLOOKUP(C98, Tbl_ColorMap[],2,false) & ")" -> 1150 - Polished Luminous Scene (Yellow) | F98: =IFERROR(__xludf.DUMMYFUNCTION("""COMPUTED_VALUE"""),"7036100-HP Recovery From Successful Guarding") -> 7036100-HP Recovery From Successful Guarding | G98: =IFERROR(__xludf.DUMMYFUNCTION("""COMPUTED_VALUE"""),"7040200-Improved Critical Hits") -> 7040200-Improved Critical Hits | H98: =IFERROR(__xludf.DUMMYFUNCTION("""COMPUTED_VALUE"""),"7040500-Improved Glintstone and Gravity Stone Damage") -> 7040500-Improved Glintstone and Gravity Stone Damage | M98: 7035100 | N98: 7040100 | O98: 7040400
A99: 1160 | B99: Polished Drizzly Scene | C99: 1 | D99: =A99 & " - " & B99 & " (" & VLOOKUP(C99, Tbl_ColorMap[],2,false) & ")" -> 1160 - Polished Drizzly Scene (Blue) | F99: =IFERROR(__xludf.DUMMYFUNCTION("""COMPUTED_VALUE"""),"7040000-Improved Initial Standard Attack") -> 7040000-Improved Initial Standard Attack | G99: =IFERROR(__xludf.DUMMYFUNCTION("""COMPUTED_VALUE"""),"7040300-Improved Throwing Pot Damage") -> 7040300-Improved Throwing Pot Damage | H99: =IFERROR(__xludf.DUMMYFUNCTION("""COMPUTED_VALUE"""),"7043000-Improved Roar & Breath Attacks") -> 7043000-Improved Roar & Breath Attacks | M99: 7036100 | N99: 7040200 | O99: 7040500
A100: 1170 | B100: Polished Drizzly Scene | C100: 1 | D100: =A100 & " - " & B100 & " (" & VLOOKUP(C100, Tbl_ColorMap[],2,false) & ")" -> 1170 - Polished Drizzly Scene (Blue) | F100: =IFERROR(__xludf.DUMMYFUNCTION("""COMPUTED_VALUE"""),"7040100-Improved Guard Counters") -> 7040100-Improved Guard Counters | G100: =IFERROR(__xludf.DUMMYFUNCTION("""COMPUTED_VALUE"""),"7040400-Improved Throwing Knife Damage") -> 7040400-Improved Throwing Knife Damage | H100: =IFERROR(__xludf.DUMMYFUNCTION("""COMPUTED_VALUE"""),"7043100-Improved Perfuming Arts") -> 7043100-Improved Perfuming Arts | M100: 7040000 | N100: 7040300 | O100: 7043000
...

Sheet Items
A1: ID | B1: English | C1: 繁體中文
A2: 1 | B2: Antique | C2: %null%
A3: 2 | B3: Antique | C3: %null%
A4: 3 | B4: Antique | C4: %null%
A5: 4 | B5: Antique | C5: %null%
A6: 5 | B6: Antique | C6: %null%
A7: 6 | B7: Antique | C7: %null%
A8: 7 | B8: %null% | C8: %null%
A9: 8 | B9: %null% | C9: %null%
A10: 9 | B10: %null% | C10: %null%
A11: 10 | B11: Murk | C11: 暗痕
A12: 11 | B12: Sovereign Sigil | C12: 為王之證
A13: 12 | B13: %null% | C13: %null%
... A2637: 2013322 | B2637: Deep Grand Tranquil Scene | C2637: 遼闊的幽靜暗淡情景

Sheet Effects
A1: ID | B1: English | C1: 繁體中文
A2: 1 | B2: %null% | C2: %null%
A3: 2 | B3: %null% | C3: %null%
A4: 3 | B4: %null% | C4: %null%
A5: 100 | B5: %null% | C5: %null%
A6: 310000 | B6: Increased Maximum HP | C6: 提升ＨＰ上限
A7: 310100 | B7: Increased Maximum FP | C7: 提升ＦＰ上限
A8: 310200 | B8: Increased Maximum Stamina | C8: 提升精力上限
A9: 310400 | B9: Increased Maximum HP | C9: 提升ＨＰ上限
A10: 310401 | B10: Increased Maximum Stamina | C10: 提升精力上限
A11: 311000 | B11: Improved Item Discovery | C11: 提升觀察力
A12: 311100 | B12: More Runes From Defeated Enemies | C12: 打倒敵人時，增加獲得的盧恩
A13: 311500 | B13: Improved Stamina Recovery | C13: 提升精力恢復速度
... A1166: 19799999 | B1166: All Options | C1166: 全選

Sheet EffectParam
A1: ID | B1: compatibilityId | C1: attachTextId | D1: overrideEffectId
A2: 0 | B2: -1 | C2: -1 | D2: 0
A3: 10000 | B3: -1 | C3: 8610100 | D3: 1
A4: 10001 | B4: -1 | C4: 7032200 | D4: 1
A5: 10002 | B5: -1 | C5: 7035900 | D5: 1
A6: 11000 | B6: -1 | C6: 7033200 | D6: 1
A7: 11001 | B7: -1 | C7: 7010200 | D7: 1
A8: 11002 | B8: -1 | C8: 7032400 | D8: 1
A9: 12000 | B9: -1 | C9: 7011000 | D9: 1
A10: 12001 | B10: -1 | C10: 7030600 | D10: 1
A11: 12002 | B11: -1 | C11: 7012000 | D11: 1
A12: 12003 | B12: -1 | C12: 7012000 | D12: 1
A13: 13000 | B13: -1 | C13: 7030900 | D13: 1
... A2080: 999999999 | B2080: -1 | C2080: -1 | D2080: 0

Sheet RelicParam
A1: ID | B1: relicColor | C1: attachEffectTableId_1 | D1: attachEffectTableId_2 | E1: attachEffectTableId_3 | F1: attachEffectTableId_curse1 | G1: attachEffectTableId_curse2 | H1: attachEffectTableId_curse3
A2: 1 | B2: 0 | C2: 501100000 | D2: -1 | E2: -1 | F2: -1 | G2: -1 | H2: -1
A3: 2 | B3: 0 | C3: 501100000 | D3: 501200000 | E3: -1 | F3: -1 | G3: -1 | H3: -1
A4: 3 | B4: 0 | C4: 501100000 | D4: 501200000 | E4: 501300000 | F4: -1 | G4: -1 | H4: -1
A5: 4 | B5: 0 | C5: 410000001 | D5: -1 | E5: -1 | F5: -1 | G5: -1 | H5: -1
A6: 5 | B6: 0 | C6: 410000002 | D6: -1 | E6: -1 | F6: -1 | G6: -1 | H6: -1
A7: 6 | B7: 0 | C7: 410000003 | D7: 410000003 | E7: 410000003 | F7: -1 | G7: -1 | H7: -1
A8: 10 | B8: 0 | C8: -1 | D8: -1 | E8: -1 | F8: -1 | G8: -1 | H8: -1
A9: 11 | B9: 0 | C9: -1 | D9: -1 | E9: -1 | F9: -1 | G9: -1 | H9: -1
A10: 20 | B10: 0 | C10: -1 | D10: -1 | E10: -1 | F10: -1 | G10: -1 | H10: -1
A11: 100 | B11: 0 | C11: 100 | D11: -1 | E11: -1 | F11: -1 | G11: -1 | H11: -1
A12: 101 | B12: 0 | C12: 200 | D12: 100 | E12: -1 | F12: -1 | G12: -1 | H12: -1
A13: 102 | B13: 0 | C13: 300 | D13: 200 | E13: 100 | F13: -1 | G13: -1 | H13: -1
... A1386: 7999999 | B1386: 0 | C1386: 707999999 | D1386: -1 | E1386: -1 | F1386: -1 | G1386: -1 | H1386: -1

Sheet EffectPoolParam
A1: ID | B1: attachEffectId
A2: 0 | B2: -1
A3: 100 | B3: 7000000
A4: 100 | B4: 7000001
A5: 100 | B5: 7000002
A6: 100 | B6: 7000100
A7: 100 | B7: 7000101
A8: 100 | B8: 7000102
A9: 100 | B9: 7000200
A10: 100 | B10: 7000201
A11: 100 | B11: 7000202
A12: 100 | B12: 7000300
A13: 100 | B13: 7000301
... A22089: 999999999 | B22089: -1
